{
  "contrasena": "0f451e8c12d0ef0125ae8a0c0714ed33214d66d7e48642859ba373024a83f481",
  "chats": {
    "Chat principal": []
  },
  "archivos": [
    {
      "nombre": "3erdepartamental.pdf",
      "contenido": {
        "tipo": "texto",
        "texto": " \nBenem\u00e9rita Universidad Aut\u00f3noma de Puebla  \nFac. de Cs. de la Computaci\u00f3n   \nAdministraci\u00f3n de Proyectos \nSecci\u00f3n: \nNRC: 26082 \nPeriodo: Oto\u00f1o 2025 \nDocente:  AMBROSIO V\u00c1ZQUEZ ALMA DELIA \n 3er Departamental \nIntegrantes de equipo: \n202337420    Osvaldo Juarez Tlamani , jt202337420@alumno.buap.mx  \n202335806    Sergio Uriel Garc\u00eda Hern\u00e1ndez , gh202335806@alm.buap.mx  \n202326531    Jahir Flores Zaragoza ,fz202326531@alumno.buap.mx  \n202268953  Toledo Dur\u00e1n David Alejandro,david.toledodu@alumno.buap.mx \n202329239   ISRAEL IGNACIO CALDER\u00d3N \nPAISANO,cp202329239@alm.buap.mx \n202319046   Maria Fernanda Aguas Rojas,  ar202319046@alumno.buap.mx  \n \n \n \n \n3ER. EX\u00c1MEN DEPARTAMENTAL \n \n \n \nMETODOLOG\u00cdAS DESARROLLADAS: PMBOK, COBIT, CMMI, ITIL \n \n \n \n \nDESARROLLO HUMANO: SOFT SKILLS \n \n \n \n \n \n \n \n \n \n \n \n \n \u00cdNDICE DEL PROYECTO: PASTILLERO INTELIGENTE \n REFLEXI\u00d3N INDIVIDUAL \nCalderon Paisano Israel Ignacio: Muchas veces ingresamos a la carrera con la mentalidad \nde s\u00f3lo aprender a programar y si compila, est\u00e1 todo hecho. Adem\u00e1s podemos ver a la \nadministraci\u00f3n de proyectos como algo de relleno que puede parecer tedioso y aburrido, sin \nembargo todo va m\u00e1s all\u00e1 de ser un \u201cprogramador solitario\u201d ya que en proyectos a gran \nescala es necesario el tiempo, costo, alcance pero sobre todo organizaci\u00f3n. Gestionar \npersonas, recursos, tiempos y avances es fundamental para desarrollar cualquier cosa y \npr\u00e1cticamente as\u00ed se rige el mundo empresarial actualmente, por eso, poner atenci\u00f3n y \nprofundizar en el contenido que existe para la administraci\u00f3n de proyectos es fundamental \npara desarrollar habilidades que potencien a nuestros conocimientos t\u00e9cnicos ya que con \nellas podremos ser profesionales de alto valor ante cualquier situaci\u00f3n o proyecto.  \n \nToledo Dur\u00e1n David Alejandro: Esta materia me pareci\u00f3 complementaria a nuestros \nconocimientos, puesto que las materias que llevo en ingenier\u00eda se basan principalmente en \nla resoluci\u00f3n de problemas, pero muchas veces como comput\u00f3logo esta resoluci\u00f3n es en \nsolitario, ya que se nos ense\u00f1a a saber salir de los problemas solos y sobre todo a \ninvestigar por nuestra cuenta. Pero esta materia cambia un poco esto, nos ense\u00f1a a \ntrabajar en equipo y sobre todo cosas como gesti\u00f3n de riesgos, gesti\u00f3n de contratos, \ncompras y adquisiciones externas; de igual forma habilidad para evaluar, dirigir y \nmonitorizar. Cosas que, por lo menos en mi caso, no hab\u00eda visto en ninguna materia a \nexcepci\u00f3n de ITIL, ya que s\u00ed he tenido que aplicar cosas para restaurar r\u00e1pidamente los \nservicios (incidentes) e identificar y resolver las causas ra\u00edz de los problemas. \nConsidero que esta visi\u00f3n integral es esencial para aplicar nuestros conocimientos t\u00e9cnicos \nen el trabajo. Nos ayuda a asegurar que los proyectos no solo sean t\u00e9cnicamente correctos, \nsino que tambi\u00e9n se completen a tiempo, sin exceder el presupuesto y cumpliendo con los \nobjetivos del negocio. \n \n \nGarc\u00eda Hern\u00e1ndez Sergio Uriel: En lo personal siempre me pareci\u00f3 que la administraci\u00f3n de \nproyectos no era algo para mi, siempre he sentido que toda la documentaci\u00f3n y todo el \ntrabajo administrativo es algo tedioso, me cuesta redactar cierto tipo de textos, pero al final \nla materia me hizo cambiar un poco mi visi\u00f3n sobre la misma, me hizo entender muchas \ncosas que yo desconoc\u00eda y que son realmente importantes a la hora de desarrollar un \nproyecto, tamb\u00eden me aport\u00f3 en el \u00e1mbito social, ya que al ser una materia en la que es \nnecesario trabajar en equipo, nos impulsa a ser m\u00e1s sociables y aprender a convivir con \ncompa\u00f1eros y trabajar en conjunto en un mismo proyecto, lo cual no es muy com\u00fan en \nnuestra carrera o al menos no a esta escala, creo firmemente que gracias a cursar esta \nmateria voy a estar m\u00e1s listo o al menos no ir\u00e9 de 0 al mundo empresarial gracias a el \ncontenido y las actividades que trabajamos este semestre. \n \n \n \n \n \n \nJahir Flores Zaragoza  \nMi perspectiva sobre el desarrollo cambi\u00f3 al enfocarme en la documentaci\u00f3n de est\u00e1ndares. \nLa materia demostr\u00f3 que la Planificaci\u00f3n de la Calidad requiere definir el Marco de Trabajo \nde TI (lenguajes, herramientas de control de versiones) antes de escribir la primera l\u00ednea de \nc\u00f3digo. La exigencia de documentar el Diagrama de Flujo del Proceso Cr\u00edtico y el flujo ITIL \nme ense\u00f1\u00f3 que la Gesti\u00f3n de Servicios obliga a crear protocolos (R1, R4) que garantizan la \nrobustez. La documentaci\u00f3n se convierte as\u00ed en la Base de Conocimiento para mitigar la \ncomplejidad t\u00e9cnica y asegurar la continuidad. \n \nOsvaldo Juarez Tlamani \nEl mayor aprendizaje fue la disciplina en la documentaci\u00f3n del Alcance y Requerimientos. \nComprend\u00ed que el \u00e9xito de la Aplicaci\u00f3n M\u00f3vil depende de la claridad de los Requerimientos \nFuncionales y No Funcionales (Interfaz simple e intuitiva). El enfoque de CMMI me ense\u00f1\u00f3 \nque la documentaci\u00f3n de las Pruebas de Usabilidad y la Gesti\u00f3n de la Medici\u00f3n son pasos \nrigurosos para alcanzar la calidad y la madurez procesal. Esto es crucial para asegurar que \nla App cumpla con el prop\u00f3sito social del Pastillero y supere la barrera de la Baja Adopci\u00f3n \n(R6) \n. \nMaria Fernanda Aguas Rojas \nLa materia demostr\u00f3 que la Gesti\u00f3n de la Informaci\u00f3n es poder. Mi rol se centr\u00f3 en la \ncreaci\u00f3n de los documentos fundacionales: Misi\u00f3n, Visi\u00f3n, KPI's y la Justificaci\u00f3n. Aprend\u00ed \nque la Matriz RACI y la Gesti\u00f3n de Interesados no son solo tablas, sino herramientas para \nformalizar la autoridad y el compromiso, que son vitales para la ejecuci\u00f3n. La Gesti\u00f3n de \nRiesgos se convirti\u00f3 en mi herramienta principal, oblig\u00e1ndome a documentar c\u00f3mo el valor \nde negocio (Mitigar R6) justifica la inversi\u00f3n metodol\u00f3gica y el Gasto Directo en RR.HH. \n \nLINK DE VIDEO \u201cDESARROLLO SOFT SKILLS\u201d \n \nSoft skills \nhttps://youtu.be/-K-n-9Vb0fI?si=Son6YbZw3Ax1Tcgz \n \nI. GESTI\u00d3N DE INTEGRACI\u00d3N DEL PROYECTO \n1.\u200b Problem\u00e1tica a resolver \nProtocolo del Proyecto 1.1. Conformaci\u00f3n de la idea (Requerimientos funcionales, no \nfuncionales y de dominio, hardware, software, tecnolog\u00edas emergentes)\u200b\n 1.2. Misi\u00f3n\u200b\n 1.3. Visi\u00f3n\u200b\n 1.4. Metas\u200b\n 1.5. Objetivos y KPI\u2019s\u200b\n 1.6. Justificaci\u00f3n\u200b\n 1.7. Estrategias\u200b\n 1.8. Estudio de viabilidad\u200b\n 1.9. Estudio de factibilidad \nII. GESTI\u00d3N DE TIEMPO DEL PROYECTO \n2.\u200b Secuencia de Actividades y Estimaci\u00f3n de la Duraci\u00f3n (Plan de 18 Semanas) \n3.\u200b Desarrollo del Cronograma en Gr\u00e1fica de Gantt \n4.\u200b Estimaci\u00f3n de recursos de las actividades \n5.\u200b Hitos y Tiempos \n6.\u200b Diagramas de Flujo (Se adjuntar\u00e1 un diagrama de alto nivel) \nIII. GESTI\u00d3N DE RECURSOS HUMANOS \n7.\u200b Planes de Gesti\u00f3n de Personal (Roles y Responsabilidades) \n8.\u200b Planes de Carrera de Personal \nIV. GESTI\u00d3N DE CALIDAD DEL PROYECTO \n9.\u200b Objetivos de Calidad \n10.\u200bKPI\u2019s de Calidad \n11.\u200bHitos de Calidad \n12.\u200bPlanificaci\u00f3n de la Calidad (Estrategias y Pruebas) \nV. GESTI\u00d3N DE COSTES DEL PROYECTO \n13.\u200bEstimaci\u00f3n de Costes del Proyecto (Gastos directos e indirectos)\u200b\n 13.1. Coste Detallado del Hardware (Prototipo \u00fanico) \nVI. GESTI\u00d3N DE ADQUISICIONES DEL PROYECTO \n14.\u200bPlanificar Compras y Adquisiciones 14.1. Estrategia de Adquisici\u00f3n de Hardware \n(Compra Directa)\u200b\n 14.2. Estrategia de Subcontrataci\u00f3n (Servicio de Ensamblaje)\u200b\n 14.3. Proceso de Adquisici\u00f3n \n \nVII. GESTI\u00d3N DE COMUNICACIONES DEL PROYECTO \n15.\u200bComunicaci\u00f3n Externa e Interna \nVIII. GESTI\u00d3N DE RIESGOS DEL PROYECTO \n16.\u200bMetodolog\u00eda de Gesti\u00f3n de Riesgos \n17.\u200bIdentificaci\u00f3n de Riesgos y Respuesta a los Riesgos 17.1. T\u00e9cnicas de Identificaci\u00f3n \nUtilizadas\u200b\n 17.2. Categor\u00edas de Riesgos Identificados (T\u00e9cnicos, Financieros, Operativos, etc.)\u200b\n 17.3. Registro de Riesgos (Risk Register)\u200b\n 17.4. Matriz Probabilidad-Impacto\u200b\n 17.5. Estrategia de Monitoreo \n \n \n \n \n \n \n \n \n \nGESTI\u00d3N DE INTEGRACI\u00d3N DEL PROYECTO \nProject Protocol \nProblem Statement   \nHigh health risks and low therapeutic adherence associated with polypharmacy in older \nadults. \nConcept \nFormation \n(Functional, \nNon-functional, \nand \nDomain \nRequirements, \nHardware, Software, Emerging Technologies) \n1. Concept Formation  \nGiven the growing challenge of polypharmacy, which primarily affects older adults and \nchronic patients, there is a need to improve adherence to pharmacological treatments and \nreduce errors in medication intake. This project consists of developing a smart pill \ndispenser system integrated with a mobile application. The dispenser will feature \nmultiple compartments that release automatically at pre-established times, while the \napplication will allow for remote medication management and treatment supervision. \nThe main objective is to guarantee that the patient takes the correct medication, in the \ncorrect dose, and at the correct time, improving their quality of life and providing peace of \nmind to their family members. \nTo guarantee the system's efficacy, emerging technologies such as the Internet of Things \n(IoT) and cloud computing will be incorporated. \n \na) Functional Requirements \n\u25cf\u200b User Profile Management: The application must allow creating and configuring user \nprofiles, including personal data and treatment details. \n\u25cf\u200b Medication Schedule Reminders: Via audible and light alarms. \n\u25cf\u200b Automatic Unlocking: The pill dispenser must automatically unlock the \ncorresponding compartment at the scheduled intake time. \n\u25cf\u200b Medication Management: The application must allow the user to add, edit, and \ndelete medications, specifying names and doses. \n\u25cf\u200b Notifications to Family/Caregivers: Sending notifications in case of a missed dose. \n\u25cf\u200b Alert Programming: The user must be able to define specific schedules for each \nmedication or group of medications. \n\u25cf\u200b Synchronization: Data between the application and the dispenser must be \nsynchronized at all times, even if the application is not open. \n\u25cf\u200b Simple and Intuitive Interface. \n \n \n \nb) Non-functional Requirements \n\u25cf\u200b High Availability: Minimal failures in alerts. \n\u25cf\u200b Low Power Consumption: Use of a long-lasting rechargeable battery. \n\u25cf\u200b Secure Connectivity: Protection of medical data. \n \n \nc) Domain Requirements \n\u25cf\u200b Knowledge of polypharmacy routines in older adults. \n\u25cf\u200b Compliance with basic medical device regulations. \n\u25cf\u200b Integration with the needs of caregivers and health personnel. \n \n \nd) Necessary Hardware \n\u25cf\u200b Pill dispenser with electronic compartments. \n\u25cf\u200b Sound/Vibration module. \n\u25cf\u200b Bluetooth/WiFi connection. \n\u25cf\u200b Sensors to detect the opening/closing of compartments. \n \ne) Necessary Software \n\u25cf\u200b Multiplatform mobile application (Android/iOS). \n\u25cf\u200b Cloud server for data storage and notifications. \n\u25cf\u200b Schedule management and reminder algorithm. \n \n \nf) Emerging Technologies \n\u25cf\u200b Artificial Intelligence (prediction of forgetfulness or routine adjustments). \n\u25cf\u200b Mobile Computing. \n\u25cf\u200b Big Data. \n\u25cf\u200b  \n \n \n \n \nMission (What is your project for at this moment?) To reduce the risks associated with \npolypharmacy in older adults through a technological solution that guarantees safety in drug \nconsumption and serves as support for caregivers and family members.\u200b\n \nVision (How does the project look in the future?) To be an innovative and accessible tool \nthat promotes safer treatments, reducing hospitalizations due to adverse effects and \nincreasing the autonomy and quality of life of older adults.\u200b\n \nGoals \n\u25cf\u200b Decrease forgetfulness, dosage errors, and dangerous interactions between \nmedications. \n\u25cf\u200b Reduce hospitalizations related to adverse effects. \n\u25cf\u200b Serve as practical support for caregivers and family members. \n\u200b\n \nObjectives and KPIs \n\u25cf\u200b General Objective: To guarantee that older adults with chronic diseases take their \nmedications safely, in the correct dose and schedule, through an integrated system \nof a smart pill dispenser and a mobile application. \n\u25cf\u200b KPIs: \n\u25cb\u200b Percentage of correctly administered doses (Target: >90%). \n\u25cb\u200b Reduction rate of hospitalizations due to medication mismanagement (Target: \n-20%). \n\u25cb\u200b Level of user and caregiver satisfaction (via surveys). \n\u25cb\u200b Improvement in user health (with patient studies). \n \nJustification \nPolypharmacy in older adults represents a growing public health problem. According to CDC \ndata, 83% of adults between 60 and 70 years old consumed at least one prescription \nmedication in the last 30 days, and approximately one-third used five or more drugs \nsimultaneously [3]. This practice increases the risk of adverse effects, dangerous \ninteractions, falls, and cognitive impairment [1][2], in addition to generating a significant \neconomic and emotional burden for both patients and caregivers. Likewise, it is estimated \nthat three out of four older adults present two or more chronic conditions (MCC) [4], which \nelevates the complexity of therapeutic management. In people with dementia, the situation is \neven more serious: 13.9% end up consuming three or more psychotropic or opioid \nmedications for more than a month, increasing the risk of dependence, overdose, and \nmortality [3]. Faced with this scenario, the development of a smart pill dispenser \nsupplemented with a mobile application constitutes an innovative and viable alternative that \nseeks to improve therapeutic adherence\u2014that is, how well a patient follows the medical \ntreatment indicated by their doctor\u2014reduce the risks of polypharmacy, and strengthen the \nquality of life of older adults. \n \n \nStrategies \u2013 How will things be done? \n\u25cf\u200b User-Centered Design with pilot tests on older adults. \n\u25cf\u200b Implementation of a simple app for family members and caregivers. \n\u25cf\u200b Marketing focused on nursing homes and clinics. \n\u200b\nViability Study \u2013 Is it really possible to realize the project? The development of the \nprototype is technically viable because it does not require the creation of new technology, \nbut rather the integration of mature, available, and low-cost hardware and software \ncomponents. \nThe central operation of the prototype will be based on the following components: \n1.\u200b Central Processing Unit (MCU): An ESP32 microcontroller will be selected. This choice is \nfundamental because the ESP32 already integrates WiFi and Bluetooth connectivity on a \nsingle chip. This eliminates the complexity of adding external modules and is crucial for \nreal-time synchronization with the mobile app and the cloud server. \n\u25cb\u200b\nWatch product (ESP32): \nhttps://www.geekfactory.mx/categoria-de-producto/tarjetas/esp32\n-esp8266/ \n2.\u200b Dispensing Mechanism: The pill dispenser will feature multiple compartments. Each \ncompartment will be secured by an individual lid or latch, which will be actuated by a \nmicro-servomotor (e.g., SG90). When the scheduled time arrives, the ESP32 firmware will \nsend a signal to the specific servo to rotate and release only the corresponding compartment.. \n\u25cb\u200b\nWatch product (Micro-servomotor SG90): \nhttps://sandorobotics.com.mx/producto/sg90/ \n3.\u200b Alert and Notification System: To meet the alarm requirement, high-brightness LEDs (visual \nalert) and a buzzer (audible alert) will be integrated. These will activate simultaneously with \nthe release of the compartment. \n\u25cb\u200b\nWatch product (LEDs): \nhttps://www.steren.com.mx/led-ultrabrillante-de-5-mm-color-blan\nco.html \n\u25cb\u200b\nWatch product (Zumbador): \nhttps://aragonelectronica.com/products/buzzer-zumbador-activo-5\nv \n4.\u200b Feedback Sensors: To verify intake and enable forgotten dose notifications, each \ncompartment will integrate sensors to detect its opening, such as limit switches. If the sensor \ndoes not detect opening after a prudent time, the ESP32 will send an alert to the cloud server, \nwhich in turn will trigger the push notification to the caregiver. \n\u25cb\u200b\nWatch product (Interruptor de l\u00edmite / Microswitch): \nhttps://natytec.com.mx/shop/electronica-cnc/micro-interruptor-s\nwitch-de-limite-completo/ \n5.\u200b Power Supply: To meet the requirement of low consumption and long duration, the system \nwill be powered by a rechargeable Lithium-Polymer (LiPo) battery. The viability of this choice \nis sustained by the use of the ESP32's \"deep-sleep\" modes, allowing the device to consume \nminimal energy while waiting for the next alarm. \n\u25cb\u200b\nWatch product (Bater\u00eda LiPo): \nhttps://sandorobotics.com.mx/producto/slw-506971/ \n6.\u200b Prototype Casing: The physical structure housing these components will be manufactured \nvia 3D printing, using materials such as PETG or PLA. This allows for rapid, iterative, and \nvery low-cost prototyping.. \n\u25cb\u200b\nWatch product (Filamento PETG): \nhttps://www.geekfactory.mx/producto/rollo-filamento-petg-175mm-\n1kg/ \nRegulatory viability is high. The device is classified as a basic medical support product. Its main \nfunction is reminder and management, not automated medical dispensing (it does not formulate or \nprepare doses, it only releases them). This exempts it from the most complex and costly certifications \nrequired for invasive or critical diagnostic medical devices, facilitating its eventual registration and \ncommercialization. \nFeasibility Study \u2013 Is it possible to implement the project? \nThe project is feasible because the skills required for its development directly coincide with the roles \nassigned to the team. Advanced research is not required, but rather the application of existing \nknowledge: \n\u25cf\u200b\nHardware and Firmware Feasibility: The Hardware/Electronics Leader (David Toledo) is \nassigned to the physical prototype design, component selection, and electronics assembly. \nThe Software Development Leader (Firmware and Backend) (Jahir Flores) is assigned to the \nESP32 firmware programming and cloud server configuration. The connection between both \nwill be made using common standards (WiFi and Bluetooth). \n\u25cf\u200b\nSoftware Feasibility (Mobile Application): The development of the multiplatform application \n(Android/iOS) is feasible. The Mobile Application Development Leader (Osvaldo Juarez) is \nassigned to this task, and the risk mitigation plan (R4) specifies the use of frameworks like \nFlutter or React Native. This strategy allows using a single code base for both platforms, \nmaking development feasible within the stipulated time.. \n\u25cf\u200b\nManagement and Quality Feasibility: The team has a Project Manager (Sergio Garc\u00eda) for \nsupervision and Business and Quality Analysts (Maria Fernanda and Israel) to ensure \nrequirements are met and quality tests are performed. \nThe feasibility of the project is significantly reinforced by the strategic decision to subcontract the \nassembly service and the manufacturing of the final casing for the pilot batch. \nThe team (students) will handle the design, validation, and prototyping (using 3D printing). However, \nby outsourcing the assembly, the team avoids a bottleneck for which they do not possess industrial \ncapacity. This allows team members to focus on their strengths (software, firmware, and \nmanagement), making the production of the pilot batch operationally feasible. \nIn addition to the team's technical capacity, the project is feasible in the real world due to three key \nexternal factors: market need, adoption strategy, and low regulatory barriers. \n1.\u200b Market Feasibility (Urgent Need): The project is not based on an invented need; it responds \nto a critical and growing public health problem: polypharmacy in older adults. With statistics \nindicating that one-third of older adults consume five or more drugs simultaneously and three \nout of four suffer from chronic diseases, there is a clear and demonstrable demand for a \nsolution that reduces the risks of forgetfulness, falls, and adverse effects. The target market \n(patients, caregivers, clinics, and nursing homes) is broad and actively seeking solutions. \n \n2.\u200b Adoption Feasibility (User-Centered): The main barrier in the real world for Health Tech \nproducts aimed at older adults is low technological adoption. This project is feasible because \nits design attacks this problem directly. The strategy of \"User-Centered Design with pilot tests \non older adults\" and the requirement for a \"Simple and Intuitive Interface\" are not optional, but \nthe core of the value proposition. The mitigation planning for risk R6 (Low adoption) includes \na \"starter kit with visual guides and assisted setup,\" demonstrating that ease of use is a pillar \nof the project. \n \n \n3.\u200b Regulatory and Commercial Feasibility: The project is commercially feasible because the \nbase technology (ESP32, sensors) is very low cost, allowing the final product to have an \naccessible and competitive price. Even more important is the regulatory viability: the device is \nclassified as a \"basic medical support product.\" Its function is reminder, not automated \nmedical dispensing. This is crucial, as it \"facilitates its future registration and \ncommercialization\" by not requiring the complex and extremely expensive certifications of \nhigh-risk medical devices. \nThe 18-week schedule is feasible precisely because the project is based on the integration \nof existing technologies (Viability) and a clear division of roles (Resource Feasibility). The \n8-week \"Development and Testing\" phase is correctly sized for the programming and \ncomponent integration tasks described. \n \n \nGesti\u00f3n de Tiempo del Proyecto \nSecuencia de Actividades y Estimaci\u00f3n de la Duraci\u00f3n \nEl proyecto est\u00e1 planificado para una duraci\u00f3n total de 18 semanas. Las actividades est\u00e1n \norganizadas por fases: \n1.\u200b Fase de Inicio (3 semanas) \n\u25cb\u200b Actividad: Indagaci\u00f3n de problemas y Conformaci\u00f3n de la idea (2 semanas) \n\u25a0\u200b Descripci\u00f3n: Se investiga el problema de la polimedicaci\u00f3n en \nadultos mayores. Se define la idea central del proyecto: un pastillero \ninteligente con una aplicaci\u00f3n m\u00f3vil. \n\u25cb\u200b Actividad: Definici\u00f3n de objetivos, KPI's, misi\u00f3n, visi\u00f3n y metas (1 semana) \n\u25a0\u200b Descripci\u00f3n: Se establecen los pilares del proyecto, incluyendo los \nobjetivos de calidad y los indicadores clave de rendimiento (KPIs) \npara medir su \u00e9xito. \n\u25cb\u200b Actividad: Estudios de viabilidad y factibilidad (1 semana) \n\u25a0\u200b Descripci\u00f3n: Se analiza si el proyecto es posible de realizar e \nimplementar desde un punto de vista t\u00e9cnico, econ\u00f3mico y social. \n\u25cb\u200b Actividad: Elaboraci\u00f3n y aprobaci\u00f3n del acta constitutiva (1 semana) \n\u25a0\u200b Descripci\u00f3n: Se formaliza el inicio del proyecto con la aprobaci\u00f3n del \nacta constitutiva. \n2.\u200b Fase de Planificaci\u00f3n (5 semanas) \n\u25cb\u200b Actividad: B\u00fasqueda y subcontrato de empresa de ensamblaje (3 semanas) \n\u25a0\u200b Descripci\u00f3n: Se identifican y seleccionan posibles proveedores para \nel ensamblaje del hardware del pastillero. \n\u25cb\u200b Actividad: Estimaci\u00f3n de costos (4 semanas) \n\u25a0\u200b Descripci\u00f3n: Se calculan los gastos directos e indirectos del \nproyecto. \n\u25cb\u200b Actividad: Planificaci\u00f3n de la calidad (3 semanas) \n\u25a0\u200b Descripci\u00f3n: Se definen los est\u00e1ndares de calidad que debe cumplir \nel producto y se crea un plan para asegurar que se cumplan. \n\u25cb\u200b Actividad: Planificaci\u00f3n de la comunicaci\u00f3n (2 semanas) \n\u25a0\u200b Descripci\u00f3n: Se definen los canales y el flujo de comunicaci\u00f3n \ninterna y externa para el equipo de trabajo y las partes interesadas. \n\u25cb\u200b Actividad: Gesti\u00f3n de riesgos (2 semanas) \n\u25a0\u200b Descripci\u00f3n: Se identifican los posibles riesgos del proyecto \n(t\u00e9cnicos, econ\u00f3micos, etc.) y se planifican las respuestas para \nmitigarlos. \n\u25cb\u200b Actividad: Gesti\u00f3n de publicidad y marketing (2 semanas) \n\u25a0\u200b Descripci\u00f3n: Se planean estrategias de marketing enfocadas en \nhogares de ancianos y cl\u00ednicas. \n3.\u200b Fase de Desarrollo y Pruebas (8 semanas) \n\u25cb\u200b Actividad: Dise\u00f1o del prototipo de hardware (3 semanas) \n\u25cb\u200b Actividad: Dise\u00f1o de la arquitectura de la aplicaci\u00f3n m\u00f3vil (4 semanas) \n\u25cb\u200b Actividad: Ensamblaje y pruebas del prototipo f\u00edsico (4 semanas) \n\u25cb\u200b Actividad: Programaci\u00f3n del firmware del pastillero (6 semanas) \n\u25cb\u200b Actividad: Desarrollo de la aplicaci\u00f3n m\u00f3vil (8 semanas) \n\u25cb\u200b Actividad: Pruebas de integraci\u00f3n del sistema (3 semanas) \n\u25cb\u200b Actividad: Pruebas piloto con usuarios (1 semana) \n4.\u200b Fase de Cierre (2 semanas) \n\u25cb\u200b Actividad: Conclusiones finales y presentaci\u00f3n del proyecto (2 semanas) \nHitos del Proyecto \n\u25cf\u200b Hito 1 (Semana 3): Fin de la fase de inicio. Se ha formalizado el proyecto con el \nacta constitutiva y los estudios de viabilidad y factibilidad. \n\u25cf\u200b Hito 2 (Semana 8): Fin de la fase de planificaci\u00f3n. Se han estimado los costos, se \nhan definido los planes de comunicaci\u00f3n, calidad y riesgos, y se ha subcontratado \nuna empresa para el ensamblaje. \n\u25cf\u200b Hito 3 (Semana 16): Prototipo funcional del pastillero y la aplicaci\u00f3n m\u00f3vil listos para \nlas pruebas finales. \n\u25cf\u200b Hito 4 (Semana 18): Presentaci\u00f3n del proyecto final. \n \n \n \n \nGesti\u00f3n de Recursos Humanos del Proyecto \nPlanes de Gesti\u00f3n de Personal \nEl equipo de proyecto est\u00e1 compuesto por estudiantes de la Facultad de Ciencias de la \nComputaci\u00f3n de la BUAP, con perfiles complementarios para cubrir todas las \u00e1reas de \ndesarrollo. Cada miembro tendr\u00e1 un rol y responsabilidades claramente definidas para \nasegurar un flujo de trabajo eficiente. \n\u25cf\u200b Gerente de Proyecto: Sergio Uriel Garc\u00eda Hern\u00e1ndez \n\u25cb\u200b Responsabilidades: \nSupervisi\u00f3n \ngeneral \ndel \nproyecto, \ngesti\u00f3n \nde \ncronogramas y recursos, coordinaci\u00f3n del equipo y comunicaci\u00f3n con las \npartes interesadas. \n\u25cb\u200b Habilidades clave: Liderazgo, organizaci\u00f3n y resoluci\u00f3n de problemas. \n\u25cf\u200b L\u00edder de Hardware/Electr\u00f3nica: Toledo Dur\u00e1n David Alejandro \n\u25cb\u200b Responsabilidades: Dise\u00f1o del prototipo f\u00edsico, selecci\u00f3n de componentes \nelectr\u00f3nicos, ensamblaje del pastillero y supervisi\u00f3n de las pruebas de \nhardware. \n\u25cb\u200b Habilidades clave: Conocimiento en electr\u00f3nica, prototipado y manejo de \nsensores. \n\u25cf\u200b L\u00edder de Desarrollo de Software (Firmware y Backend): Jahir Flores Zaragoza \n\u25cb\u200b Responsabilidades: Programaci\u00f3n del firmware del pastillero, desarrollo de \nla l\u00f3gica de sincronizaci\u00f3n y configuraci\u00f3n del servidor en la nube. \n\u25cb\u200b Habilidades clave: Programaci\u00f3n embebida (firmware), gesti\u00f3n de bases de \ndatos y servicios en la nube. \n\u25cf\u200b L\u00edder de Desarrollo de Aplicaciones M\u00f3viles: Osvaldo Juarez Tlamani \n\u25cb\u200b Responsabilidades: Desarrollo de la aplicaci\u00f3n m\u00f3vil multiplataforma \n(Android/iOS), implementaci\u00f3n de la interfaz de usuario (UI) y gesti\u00f3n de \nnotificaciones. \n\u25cb\u200b Habilidades clave: Desarrollo de aplicaciones m\u00f3viles (Flutter/React Native) \ny dise\u00f1o de UI/UX. \n\u25cf\u200b Analistas de Negocio y Calidad: Maria Fernanda Aguas Rojas e Israel Ignacio \nCalder\u00f3n  Paisano \n\u25cb\u200b Responsabilidades: Recopilaci\u00f3n de requerimientos, definici\u00f3n de KPIs, \nrealizaci\u00f3n de pruebas de calidad y an\u00e1lisis de la viabilidad social y de  \nPlanes de carrera de personal.\u200b\n \nEl Plan de Carrera para el equipo se centra en la adquisici\u00f3n y especializaci\u00f3n de \nhabilidades clave en el sector de tecnolog\u00eda y salud, preparando a los integrantes para roles \navanzados dentro de una futura organizaci\u00f3n o en el mercado laboral. \n \n \n \n \nBeneficios Clave del Plan de Carrera \n1.\u200b Portafolio de Alto Nivel: Cada miembro obtendr\u00e1 un producto f\u00edsico (el pastillero) y \nun producto de software (la aplicaci\u00f3n) totalmente documentado, que servir\u00e1 como \nprueba tangible de sus capacidades ante futuros empleadores. \n2.\u200b Exposici\u00f3n a Tecnolog\u00edas Emergentes: El equipo adquiere experiencia pr\u00e1ctica en \nel Internet de las Cosas (IoT) y la computaci\u00f3n en la nube , con una visi\u00f3n a futuro \nen la implementaci\u00f3n de Inteligencia Artificial (IA). \n3.\u200b Habilidades Blandas: El plan promueve la comunicaci\u00f3n efectiva y el\u200b\n dise\u00f1o centrado en el usuario, cruciales para el \u00e9xito en el desarrollo de \ndispositivos m\u00e9dicos. \n \nGerente de Proyecto \n(Sergio Uriel G. H.) \nCertificaci\u00f3n en \ngesti\u00f3n de proyectos \n(e.g., Scrum Master). \nGerente de Programa \no Director de \nOperaciones \n(enfocado en \nescalamiento). \nLiderazgo de equipos \nt\u00e9cnicos y gesti\u00f3n de \nriesgos estrat\u00e9gicos. \nL\u00edder de \nHardware/Electr\u00f3nica \n(Toledo Dur\u00e1n D. A.) \nInvestigaci\u00f3n y \ndesarrollo de la \nversi\u00f3n 2.0 del \npastillero con IA. \nIngeniero Senior de \nI+D o Especialista en \nIoT/Electr\u00f3nica \nM\u00e9dica. \nOptimizaci\u00f3n de bajo \nconsumo de energ\u00eda y \nminiaturizaci\u00f3n de \ncomponentes. \nL\u00edder de Desarrollo de \nSoftware (Firmware y \nBackend) (Jahir \nFlores Z.) \nProfundizaci\u00f3n en \nseguridad de datos \nm\u00e9dicos y \narquitectura en la \nnube (AWS/Azure). \nArquitecto de \nSoluciones Cloud o \nIngeniero de Firmware \nAvanzado. \nAlta disponibilidad , \nseguridad y desarrollo \nde algoritmos de \ngesti\u00f3n de horarios. \nL\u00edder de Desarrollo de \nAplicaciones M\u00f3viles \n(Osvaldo J. T.) \nEspecializaci\u00f3n en \nUX/UI para adultos \nmayores y desarrollo \nmultiplataforma \navanzado \n(iOS/Android). \nEspecialista en \nExperiencia de \nUsuario (UX) o L\u00edder \nT\u00e9cnico M\u00f3vil. \nAnalistas de Negocio \ny Calidad (Maria \nFernanda A. R. y \nISRAEL I. C. P.) \nAdquisici\u00f3n de \nconocimiento de \nnormativas de \ndispositivos m\u00e9dicos y \nestudio de viabilidad \necon\u00f3mica avanzada. \nConsultor de \nHealthTech o \nEspecialista en \nCumplimiento y \nCalidad. \nAseguramiento de la \nCalidad (QA), an\u00e1lisis \nde KPIs y estrategias \nde mercado. \nGESTI\u00d3N DE CALIDAD DEL PROYECTO \nOBJETIVOS \nGarantizar que el pastillero funcione con un 90% de confiabilidad en las alertas sonoras y \nvisuales. \nAsegurar que la aplicaci\u00f3n m\u00f3vil tenga una probabilidad de error menor al 1% en la gesti\u00f3n \nde los medicamentos. \nKPI\u2019S DE CALIDAD \n\u25cf\u200b Probabilidad de fallos del hardware: < 2% en pruebas de estr\u00e9s \n\u25cf\u200b Tiempo de respuesta de la app: < 3 segundos en 90% de las operaciones \n\u25cf\u200b Satisfacci\u00f3n del usuario: > 85% en pruebas piloto con adultos mayores \n\u25cf\u200b Cobertura de pruebas: > 90% del c\u00f3digo fuente \n\u25cf\u200b Probabilidad de sincronizaci\u00f3n exitosa: > 98% entre app y pastillero \nHITOS DE CALIDAD \n\u25cf\u200b Semana 6: Revisi\u00f3n de especificaciones t\u00e9cnicas y est\u00e1ndares de desarrollo \n\u25cf\u200b Semana 10: Pruebas de usabilidad con 5 adultos mayores (prototipo inicial) \n\u25cf\u200b Semana 14: Pruebas de estr\u00e9s del sistema integrado (hardware + software) \n\u25cf\u200b Semana 16: Validaci\u00f3n final de cumplimiento de todos los requerimientos \nPLANIFICACI\u00d3N DE LA CALIDAD \n\u25cf\u200b Revisiones t\u00e9cnicas semanales: An\u00e1lisis del c\u00f3digo y documentaci\u00f3n. \n\u25cf\u200b Pruebas automatizadas: Ejecuci\u00f3n diaria de pruebas unitarias y de integraci\u00f3n. \n\u25cf\u200b Pruebas de usabilidad mensuales: Sesiones con usuarios reales (adultos mayores \no cuidadores). \n\u25cf\u200b Control de versiones: Uso de Git para gestionar cambios en el c\u00f3digo. \n\u25cf\u200b Documentaci\u00f3n de procesos: Registro de todos los hallazgos y mejoras. \n\u25cf\u200b Capacitaci\u00f3n del equipo: Sesiones sobre est\u00e1ndares de calidad y mejores \npr\u00e1cticas. \n \n \nGesti\u00f3n de costes del proyecto \nEl estimado de costes se divide en dos categor\u00edas principales: Gastos Directos, que son \ndirectamente atribuibles al producto (hardware, software, subcontrataci\u00f3n), y Gastos \nIndirectos, que son necesarios para la gesti\u00f3n y operaci\u00f3n del proyecto (recursos humanos, \noverhead). \n1. Estimaci\u00f3n de Gastos Directos (Capital y Desarrollo) \nEstos costos est\u00e1n directamente relacionados con la producci\u00f3n del prototipo funcional y la \ninfraestructura del sistema. Se considera un coste inicial bajo, lo cual es competitivo en el \nmercado de dispositivos m\u00e9dicos b\u00e1sicos. \n \nConcepto \nDetalle \nCoste Estimado \n(MXN) \nJustificaci\u00f3n \nHardware para Prototipo Componentes \npara \nel \npastillero \n(Microcontrolador, \nServos, Carcasa 3D) \n3,500 \nComponentes de f\u00e1cil \nacceso y bajo costo. \nInfraestructura \nde \nSoftware \nLicencia de servidor en la \nnube (primer a\u00f1o) \n5,000 \nNecesario \npara \nla \nsincronizaci\u00f3n y la alta \ndisponibilidad. \nPlataformas \nde \nDesarrollo \nLicencias para herramientas \nde dise\u00f1o UI/UX y desarrollo \nmultiplataforma \n3,500 \nHerramientas \nnecesarias \npara \nla \ninterfaz \nsimple \ne \nintuitiva. \nPruebas y Certificaci\u00f3n \nB\u00e1sica \nMateriales para pruebas de \nintegraci\u00f3n y simulaci\u00f3n de \nnormativas \n2,500 \nGastos esenciales para \nverificar la calidad. \nSubcontrataci\u00f3n \n(Ensamblaje) \nCoste \nestimado \nde \nnegociaci\u00f3n para el lote piloto \n(externo) \n6,000 \nCoste relacionado con \nla \nactividad \nde \nplanificaci\u00f3n \nde \nsubcontrato. \nRecursos \nHumanos \n(Costo Te\u00f3rico/Beca) \nValoraci\u00f3n del tiempo de los \n6 integrantes del equipo (18 \nsemanas \na \n3,000 \nMXN/semana) \n54,000 \nCoste directo de la \nmano \nde \nobra \nproductiva \ndel \nproyecto. \nSubtotal \nGastos \nDirectos \n \n74,500 \n \nBuffer de Contingencia \n(15%) \n \n11,175 \nProtecci\u00f3n \nfinanciera \nante \nvolatilidad \ndel \nmercado. \nTOTAL \nGASTOS \nDIRECTOS \n \n85,675 \n \n \n2. Estimaci\u00f3n de Gastos Indirectos (Operaci\u00f3n y Gesti\u00f3n) \nEstos costes se centran en el valor del recurso humano y los gastos operativos del \nproyecto. \n \n \n \nConcepto \nDetalle \nDuraci\u00f3n \n(Semanas) \nCoste por \nSemana (MXN) \nCoste Total \n(MXN) \nComunicaciones \ny \nMarketing \nElaboraci\u00f3n \nde \nmaterial \npublicitario \ndigital \ny \nmarketing inicial \n18 \n500 \n9,000 \nVi\u00e1ticos y Log\u00edstica \nReuniones \nde \nequipo, \ntransporte y materiales para \npruebas piloto \n18 \n400 \n7,200 \nGastos de Oficina y \nSuministros \nMaterial \nde \npapeler\u00eda, \nimpresiones \n(documentaci\u00f3n), \nservicios \nb\u00e1sicos \n(luz/internet \ncompartidos). \n18 \n200 \n3,600 \nGesti\u00f3n y Overhead \nCostos \nde \ngesti\u00f3n \nde \nproyecto y amortizaci\u00f3n de \nequipos \npropios \n(computadoras). \n18 \n400 \n7,200 \nSubtotal \nGastos \nIndirectos \n \n \n \n27,000 \nBuffer de Contingencia \n(15%) \n \n \n \n4,050 \nTOTAL \nGASTOS \nINDIRECTOS \n \n \n \n31,050 \n \n3. Resumen de Costes del Proyecto \nEl coste total estimado para la fase de documentaci\u00f3n y desarrollo del prototipo funcional \ndel Pastillero Inteligente es el siguiente: \n \n \nCategor\u00eda \nSubtotal (MXN) \nBuffer 15% (MXN) \nTotal con Buffer (MXN) \nGastos Directos \n74,500 \n11,175 \n85,675 \nGastos Indirectos \n27,000 \n4,050 \n31,050 \nCOSTE TOTAL DEL \nPROYECTO \n101,500 \n15,225 \n116,725 \n \nEsta estimaci\u00f3n asegura que el desarrollo del prototipo inicial se puede realizar con una \ninversi\u00f3n controlada, confirmando la viabilidad econ\u00f3mica del proyecto. \n \nGesti\u00f3n de Adquisiciones del Proyecto \nEl objetivo de esta gesti\u00f3n es asegurar que los bienes y servicios externos necesarios para \nel proyecto (principalmente el hardware y el servicio de ensamblaje) se adquieran de \nmanera oportuna, rentable y con la calidad requerida. \nPlanificar Compras y Adquisiciones \nLa estrategia de adquisiciones se centrar\u00e1 en dos tipos principales de contratos: la compra \ndirecta de componentes electr\u00f3nicos y la subcontrataci\u00f3n de servicios de fabricaci\u00f3n \ny ensamblaje. \n1. Estrategia de Adquisici\u00f3n de Hardware (Compra Directa) \n\u25cf\u200b Alcance: Adquisici\u00f3n de todos los componentes electr\u00f3nicos de bajo coste para el \nprototipo (microcontroladores, sensores, servomotores SG90, bater\u00edas, etc.). \n\u25cf\u200b Tipo de Contrato: Orden de Compra Fija (Fixed-Price Purchase Order). Se \nutilizar\u00e1n plataformas en l\u00ednea especializadas (como las usadas en la justificaci\u00f3n de \ncostes) para asegurar precios unitarios bajos y transparentes. \n\u25cf\u200b Justificaci\u00f3n: El bajo coste y la alta disponibilidad de los componentes permiten \nuna compra directa r\u00e1pida y eficiente, lo que minimiza el riesgo de sobrecostos en la \nfase de prototipado. \n2. Estrategia de Subcontrataci\u00f3n \n\u25cf\u200b Alcance: Contrataci\u00f3n de una empresa o taller especializado para la fabricaci\u00f3n del \nlote piloto de la carcasa final y el ensamblaje de la electr\u00f3nica, despu\u00e9s de validar el \nprototipo. \n\u25cf\u200b Tipo de Contrato: Contrato de Precio Fijo (Fixed-Price Contract). El \nsubcontratista cotizar\u00e1 un precio fijo para la producci\u00f3n de un lote de prueba (ej. 50 \nunidades), asumiendo el riesgo de los costes. \n\u25cf\u200b Justificaci\u00f3n: La subcontrataci\u00f3n es esencial porque el equipo de proyecto no tiene \nla capacidad industrial para la producci\u00f3n en masa de carcasas de alta calidad ni el \ntiempo para el ensamblaje de grandes lotes. Esto garantiza un acabado profesional \npara el producto final. \nProceso de Adquisici\u00f3n \n1.\u200b Requerimiento de Compras: El L\u00edder de Hardware/Electr\u00f3nica genera la lista de \nmateriales (BOM) y especificaciones t\u00e9cnicas. \n2.\u200b Solicitud de Informaci\u00f3n (RFI): Para la subcontrataci\u00f3n de ensamblaje, se \nenviar\u00e1n solicitudes a tres proveedores potenciales para evaluar su capacidad \nt\u00e9cnica y experiencia. \n3.\u200b Selecci\u00f3n de Proveedor: El Gerente de Proyecto y el L\u00edder de Hardware \nevaluar\u00e1n las cotizaciones y seleccionar\u00e1n a los proveedores con la mejor relaci\u00f3n \ncalidad-precio y tiempo de entrega. \n4.\u200b Administraci\u00f3n de Contratos: El Gerente de Proyecto monitorear\u00e1 activamente el \ndesempe\u00f1o de los proveedores subcontratados para asegurar el cumplimiento de \nlos t\u00e9rminos y plazos establecidos en el plan de tiempo. \n \n \nGESTI\u00d3N DE COMUNICACIONES DEL PROYECTO \nEl Plan de Gesti\u00f3n de Comunicaciones asegura que la informaci\u00f3n relevante sea generada, \ndistribuida, almacenada y dispuesta de forma adecuada y oportuna a lo largo de las 18 \nsemanas del proyecto. \n \n1. Comunicaci\u00f3n Interna (Equipo de Proyecto) \nLa comunicaci\u00f3n interna se enfoca en la coordinaci\u00f3n efectiva, la resoluci\u00f3n de problemas y \nla gesti\u00f3n del cronograma. \n \n\u00bfQu\u00e9? \n\u00bfQui\u00e9n? \n\u00bfA Qui\u00e9n? \n\u00bfCu\u00e1ndo? \nCanal/M\u00e9todo \nReuni\u00f3n de \nEstatus \nSemanal \nGerente de \nProyecto \nTodo el Equipo \nLunes por la \nma\u00f1ana (1 \nhora) \nVideoconferencia y \nActa de Reuni\u00f3n \nReporte de \nAvance \nSemanal \nL\u00edderes de \u00c1rea \nGerente de \nProyecto \nViernes al \nfinal del d\u00eda \nCorreo Electr\u00f3nico y \nDocumento \nCompartido \nAlertas de \nRiesgos/Depen\ndencias \nL\u00edderes de \u00c1rea \nGerente de \nProyecto y \u00c1rea \nAfectada \nInmediatame\nnte \nMensajer\u00eda \nInstant\u00e1nea \n(WhatsApp/Slack) \nRevisiones de \nC\u00f3digo/Dise\u00f1o \nDesarrolladores/\nL\u00edder de \nHardware \nEquipo de \nDesarrollo \nBajo \nDemanda \nHerramientas de \nControl de Versiones \n(Git) y Documentos \nCompartidos \nEstrategia Clave: Se priorizar\u00e1 la comunicaci\u00f3n formal para las decisiones de dise\u00f1o y \nlas alertas de riesgos, y la comunicaci\u00f3n informal (mensajer\u00eda instant\u00e1nea) para la \ncoordinaci\u00f3n diaria y la resoluci\u00f3n r\u00e1pida de problemas t\u00e9cnicos. \n \n2. Comunicaci\u00f3n Externa (Partes Interesadas y Cuidadores) \nLa comunicaci\u00f3n externa est\u00e1 dirigida a los usuarios finales (adultos mayores, cuidadores) y \na las partes interesadas que eval\u00faan la viabilidad del proyecto (docentes, posibles \ninversionistas o socios comerciales). \n \n\u00bfQu\u00e9? \n\u00bfQui\u00e9n? \n\u00bfA Qui\u00e9n? \n\u00bfCu\u00e1ndo? \nCanal/M\u00e9todo \nManual de \nUsuario y \nCuidado \nAnalistas \nde Negocio \nUsuarios Finales \n(Simulados) y \nCuidadores \nFase de Pruebas \nPiloto (Semana \n18) \nDocumento Digital y \nContenido In-App \nNotificaci\u00f3n \nde \nOlvido/Dosis \nSistema \n(Pastillero/\nApp) \nFamiliares/Cuidadore\ns \nEn Tiempo Real \nNotificaci\u00f3n Push en \nla Aplicaci\u00f3n M\u00f3vil \nPresentaci\u00f3n \nde Avance \nGerente de \nProyecto \nDocente/Stakeholders \nPrincipales \nAl finalizar cada \nFase \nPresentaci\u00f3n Formal \n(Diapositivas y \nDemo) \nMaterial de \nMarketing \nInicial \nAnalistas \nde Negocio \nHogares de Ancianos \ny Cl\u00ednicas \n(Simulados) \nFase de \nPlanificaci\u00f3n \n(Semanas 7-8) \nCorreo Electr\u00f3nico y \nMaterial Impreso \nCotizaciones \ny Pedidos \nL\u00edder de \nHardware \nProveedores de \nComponentes \nSeg\u00fan el \ncronograma de \nadquisiciones \nCorreo Electr\u00f3nico o \nllamada de \nseguimiento \n \n3.Protocolo de comunicaci\u00f3n de crisis  \n \nNivel \nProblema \n(Ejemplos) \n\u00bfQui\u00e9n \nalerta? \n\u00bfA qui\u00e9n? \nTiempo \nMedio \n1  \nFallo total del \nPrototipo \nQuien detecte \nel problema \nGerente/ \nL\u00edderes \nt\u00e9cnicos \nM\u00e1ximo 1 \nhora despu\u00e9s \nde la \ndetecci\u00f3n  \nCorreo \nElectr\u00f3nico/Vi\nsita \npresencial \n2 \nRetraso de 1 \nsemana \nL\u00edder del \u00e1rea \nafectada \nGerente/ \n\u00c1reas \ninvolucradas \nNo mayor a 1 \nd\u00eda \nCorreo \nElectr\u00f3nico/Vi\nsita \npresencial \n3 \nFallo en alguna \nfuncionalidad \nResponsable \nde dicha tarea \nL\u00edder de \u00e1rea \nDurante la \nreuni\u00f3n \nprogramada \nm\u00e1s pr\u00f3xima \nCorreo \nElectr\u00f3nico/Vi\nsita \npresencial \n \n \nGESTI\u00d3N DE RIESGOS DEL PROYECTO \nLa gesti\u00f3n de riesgos en proyectos consiste en identificar, analizar y dar respuesta a \neventos inciertos que pueden impactar los objetivos del proyecto en alcance, tiempo, costo \ny calidad. Seg\u00fan las pr\u00e1cticas del PMBOK, este proceso busca minimizar amenazas y \nmaximizar oportunidades, reduciendo la incertidumbre y aumentando la probabilidad de \n\u00e9xito del proyecto. \n1. Metodolog\u00eda de Gesti\u00f3n de Riesgos \nEn nuestro proyecto se seguir\u00e1 el enfoque recomendado por el PMBOK:\u200b\n 1. Planificar la gesti\u00f3n de riesgos \u2192 establecer c\u00f3mo se gestionan.\u200b\n 2. Identificar los riesgos \u2192 recopilar riesgos potenciales en todas las categor\u00edas.\u200b\n 3. An\u00e1lisis cualitativo de riesgos \u2192 evaluar probabilidad e impacto.\u200b\n 4. An\u00e1lisis cuantitativo de riesgos (cuando sea necesario).\u200b\n 5. Planificar la respuesta a los riesgos \u2192 definir acciones y responsables.\u200b\n 6. Monitorear y controlar los riesgos \u2192 actualizar el registro y hacer seguimiento peri\u00f3dico. \n2. Identificaci\u00f3n de Riesgos \n2.1 T\u00e9cnicas de Identificaci\u00f3n Utilizadas \nPara garantizar una identificaci\u00f3n exhaustiva de riesgos, se aplicaron las siguientes t\u00e9cnicas \nrecomendadas por el PMBOK: \na) Tormenta de Ideas (Brainstorming) \n\u25cf\u200b Sesiones colaborativas con todo el equipo del proyecto \n\u25cf\u200b Identificaci\u00f3n de riesgos desde diferentes perspectivas (t\u00e9cnica, financiera, \noperativa) \n\u25cf\u200b Participaci\u00f3n de los 6 miembros del equipo con roles complementarios \nb) An\u00e1lisis SWOT/FODA \n\u25cf\u200b Fortalezas: Equipo multidisciplinario, tecnolog\u00eda IoT disponible, mercado objetivo \namplio \n\u25cf\u200b Oportunidades: Creciente poblaci\u00f3n adulta mayor, inter\u00e9s en tecnolog\u00edas de salud \n\u25cf\u200b Debilidades: Equipo estudiantil sin experiencia previa en dispositivos m\u00e9dicos \n\u25cf\u200b Amenazas: Regulaciones m\u00e9dicas estrictas, competencia de grandes empresas \nc) Revisi\u00f3n de Documentaci\u00f3n \n\u25cf\u200b An\u00e1lisis de proyectos similares de dispositivos IoT m\u00e9dicos \n\u25cf\u200b Revisi\u00f3n de estad\u00edsticas del CDC sobre polimedicaci\u00f3n \n\u25cf\u200b Estudio de normativas COFEPRIS, FDA y CE para dispositivos m\u00e9dicos \nd) Entrevistas con Expertos \n\u25cf\u200b Consulta con profesionales de salud sobre necesidades reales \n\u25cf\u200b Asesor\u00eda t\u00e9cnica en IoT y desarrollo de hardware \n\u25cf\u200b Retroalimentaci\u00f3n de potenciales usuarios (adultos mayores y cuidadores) \n \ne) An\u00e1lisis de Supuestos \n\u25cf\u200b Supuesto: Los adultos mayores aceptar\u00e1n usar tecnolog\u00eda \u2192 Riesgo R6 \n\u25cf\u200b Supuesto: Conectividad estable en hogares \u2192 Riesgo R9 \n\u25cf\u200b Supuesto: Disponibilidad de componentes electr\u00f3nicos \u2192 Riesgo R3, R5 \nf) Listas de Verificaci\u00f3n (Checklists) \n\u25cf\u200b Checklist de riesgos t\u00e9cnicos en proyectos IoT \n\u25cf\u200b Checklist de riesgos regulatorios en dispositivos m\u00e9dicos \n\u25cf\u200b Checklist de riesgos de gesti\u00f3n de proyectos \n2.2 Categor\u00edas de Riesgos Identificados \nSe han identificado 9 riesgos principales distribuidos en 6 categor\u00edas: \nA. RIESGOS T\u00c9CNICOS (3 riesgos) \nR1 - Fallo en la comunicaci\u00f3n IoT \n\u25cf\u200b Causa: Interferencias electromagn\u00e9ticas, problemas de red, fallas de hardware \n\u25cf\u200b Evento: App m\u00f3vil y pastillero no se sincronizan correctamente \n\u25cf\u200b Efecto: P\u00e9rdida de datos, notificaciones fallidas, desconfianza del usuario \n\u25cf\u200b Trigger: Tasa de desconexi\u00f3n > 5%, reportes de usuarios sobre falta de \nsincronizaci\u00f3n \nSoluci\u00f3n:Para garantizar la confiabilidad del sistema de comunicaci\u00f3n, implementaremos \nuna arquitectura h\u00edbrida que combine WiFi y Bluetooth, respaldada por colas de mensajes \ncon reintentos autom\u00e1ticos seg\u00fan los patrones de dise\u00f1o para sistemas IoT resilientes. El \ndispositivo contar\u00e1 con almacenamiento local que permitir\u00e1 sincronizaci\u00f3n posterior en caso \nde p\u00e9rdida temporal de conexi\u00f3n, mientras que indicadores visuales claros informar\u00e1n al \nusuario sobre el estado de la conectividad en todo momento. Esta soluci\u00f3n multicapa \nasegura que ning\u00fan dato cr\u00edtico se pierda y que el sistema permanezca funcional incluso \nante fallos intermitentes de red, proporcionando la robustez necesaria para un dispositivo de \nmonitoreo de salud. \nR2 - Bater\u00eda defectuosa o baja duraci\u00f3n \n\u25cf\u200b Causa: Componentes de baja calidad, consumo energ\u00e9tico no optimizado \n\u25cf\u200b Evento: Pastillero se apaga antes del tiempo esperado (< 7 d\u00edas) \n\u25cf\u200b Efecto: P\u00e9rdida de alertas, baja confiabilidad del dispositivo \n\u25cf\u200b Trigger: Duraci\u00f3n de bater\u00eda < 85% de lo especificado en pruebas \nSoluci\u00f3n:Abordaremos el desaf\u00edo energ\u00e9tico mediante una estrategia integral que incluye \nla implementaci\u00f3n de modos de sue\u00f1o profundo entre operaciones y la selecci\u00f3n de \nbater\u00edas de litio-pol\u00edmero de alta densidad energ\u00e9tica. Realizaremos mediciones reales para \ndise\u00f1ar un perfil de consumo optimizado que maximice la autonom\u00eda del dispositivo. Esta \ncombinaci\u00f3n de optimizaci\u00f3n de software y hardware adecuado garantiza que el dispositivo \nmantenga operatividad continua sin generar preocupaci\u00f3n en los usuarios sobre la bater\u00eda. \nB. RIESGOS FINANCIEROS (1 riesgo) \nR3 - Sobrecostos en componentes electr\u00f3nicos \n\u25cf\u200b Causa: Aumento de precios en mercado global, escasez de semiconductores \n\u25cf\u200b Evento: Costo de prototipado supera el presupuesto estimado \n\u25cf\u200b Efecto: +15% del presupuesto original, necesidad de recortes \n\u25cf\u200b Trigger: Cotizaciones de proveedores > 10% del precio estimado \nSoluci\u00f3n: Mitigaremos la volatilidad de precios en componentes mediante una estrategia de \ncadena de suministro diversificada que incluye acuerdos con m\u00faltiples proveedores. \nMantendremos un buffer presupuestario del 15% para absorber fluctuaciones de mercado e \nimplementaremos un programa de pre-compra para componentes cr\u00edticos que nos permita \naprovechar precios favorables y asegurar disponibilidad. Este enfoque proactivo de gesti\u00f3n \nfinanciera y de suministro protege el proyecto contra disrupciones del mercado y mantiene \nlos costos controlados dentro de m\u00e1rgenes predecibles. \nC. RIESGOS OPERATIVOS (2 riesgos) \nR4 - Retraso en desarrollo de aplicaci\u00f3n m\u00f3vil \n\u25cf\u200b Causa: Complejidad t\u00e9cnica subestimada, problemas de compatibilidad iOS/Android \n\u25cf\u200b Evento: Entregables de app m\u00f3vil se retrasan \n\u25cf\u200b Efecto: +4 semanas al cronograma (22% de incremento) \n\u25cf\u200b Trigger: Desviaci\u00f3n del cronograma > 1 semana en fase de desarrollo \nSoluci\u00f3n: Para asegurar entregas puntuales del desarrollo m\u00f3vil, utilizaremos frameworks \ncross-platform como React Native o Flutter que permiten desarrollo simult\u00e1neo para iOS y \nAndroid, reduciendo significativamente los tiempos ,adem\u00e1s el prototipado r\u00e1pido y pruebas \nde usabilidad tempranas nos permitir\u00e1n detectar y corregir problemas antes de que se \nconviertan en retrasos costosos. \nR5 - Dependencia de proveedor de ensamblaje externo \n\u25cf\u200b Causa: \u00danico proveedor contratado tiene problemas operativos o financieros \n\u25cf\u200b Evento: Retrasos en entrega de prototipos ensamblados \n\u25cf\u200b Efecto: Extensi\u00f3n del cronograma, imposibilidad de realizar pruebas a tiempo \n\u25cf\u200b Trigger: Proveedor notifica retrasos o incumplimientos de SLA \nSoluci\u00f3n: Eliminaremos el riesgo de dependencia \u00fanica mediante la calificaci\u00f3n y \ncontrataci\u00f3n de al menos dos proveedores de ensamblaje, respaldados por acuerdos de \nnivel \nde \nservicio \n(SLA) \ncon \npenalizaciones \nclaras \nque \nincentiven \nel \ncumplimiento.mantendremos un inventario de seguridad de componentes cr\u00edticos y \ndesarrollaremos capacidad limitada de ensamblaje interno para situaciones de emergencia \no producciones piloto. Esta redundancia operativa garantiza continuidad de producci\u00f3n ante \ncualquier fallo o incumplimiento de un proveedor espec\u00edfico, protegiendo los plazos de \nentrega al mercado. \n \nD. RIESGOS DE MERCADO (1 riesgo) \nR6 - Baja adopci\u00f3n por parte de adultos mayores \n\u25cf\u200b Causa: Complejidad percibida, resistencia al cambio tecnol\u00f3gico, miedo a \ndispositivos \n\u25cf\u200b Evento: Usuarios objetivo rechazan o abandonan el uso del sistema \n\u25cf\u200b Efecto: Fracaso comercial del producto, inversi\u00f3n sin retorno \n\u25cf\u200b Trigger: Tasa de abandono > 30% en pruebas piloto, satisfacci\u00f3n < 60% \nSoluci\u00f3n:Ofreceremos soporte telef\u00f3nico especializado 24/7 operado por personal \nentrenado en comunicaci\u00f3n con adultos mayores, y cada dispositivo incluir\u00e1 un kit de inicio \ncon gu\u00edas visuales y setup asistido que simplifique la primera experiencia. Este enfoque \nhol\u00edstico que combina dise\u00f1o accesible con soporte humano cercano elimina las barreras \ntecnol\u00f3gicas t\u00edpicas que enfrentan los adultos mayores, transformando la tecnolog\u00eda en una \nherramienta amigable y confiable. \nE. RIESGOS DE RECURSOS HUMANOS (1 riesgo) \nR7 - Rotaci\u00f3n de personal clave del equipo \n\u25cf\u200b Causa: Graduaci\u00f3n, ofertas laborales externas, insatisfacci\u00f3n, carga acad\u00e9mica \n\u25cf\u200b Evento: Miembro clave abandona el proyecto (especialmente l\u00edderes t\u00e9cnicos) \n\u25cf\u200b Efecto: P\u00e9rdida de conocimiento, retrasos, errores por falta de experiencia \n\u25cf\u200b Trigger: Expresi\u00f3n de intenci\u00f3n de salida, ausencias frecuentes, baja participaci\u00f3n \nSoluci\u00f3n:Mantendremos documentaci\u00f3n exhaustiva de procesos y arquitectura que facilite \nla incorporaci\u00f3n de nuevos miembros, mientras que un plan de desarrollo profesional \nvinculado al proyecto incentivar\u00e1 la permanencia del talento clave al ofrecer crecimiento \nsignificativo. Los acuerdos de confidencialidad y no competencia proteger\u00e1n la propiedad \nintelectual desarrollada, asegurando que la inversi\u00f3n en capacitaci\u00f3n no beneficie a \ncompetidores directos. \nF. RIESGOS EXTERNOS (2 riesgos) \nR8 - Cambios en normativas de dispositivos m\u00e9dicos \n\u25cf\u200b Causa: Actualizaci\u00f3n de regulaciones COFEPRIS, FDA o CE durante el desarrollo \n\u25cf\u200b Evento: Nuevos requisitos legales no contemplados inicialmente \n\u25cf\u200b Efecto: Necesidad de redise\u00f1o, sobrecostos, retrasos en certificaci\u00f3n \n\u25cf\u200b Trigger: Publicaci\u00f3n de nuevas normas NOM, directivas europeas o gu\u00edas FDA \nNos adelantamos a cambios regulatorios mediante la participaci\u00f3n activa en asociaciones \ndel sector que nos mantendr\u00e1n informados sobre tendencias normativas, siguiendo la gu\u00eda \nde la FDA sobre control de dise\u00f1o. Nuestro dise\u00f1o modular permitir\u00e1 adaptaciones r\u00e1pidas \nante nuevos requisitos sin necesidad de redise\u00f1o completo, mientras que la consultor\u00eda \nespecializada en regulaci\u00f3n m\u00e9dica validar\u00e1 continuamente nuestro cumplimiento. Esta \nvigilancia regulatoria proactiva y arquitectura adaptable nos permite responder \u00e1gilmente a \ncambios normativos, convirtiendo una potencial amenaza en una ventaja competitiva sobre \nempresas menos preparadas. \nR9 - Fallas de conectividad en usuarios finales \n\u25cf\u200b Causa: Infraestructura de internet deficiente en hogares objetivo \n\u25cf\u200b Evento: Sistema no puede sincronizar con servidor en la nube \n\u25cf\u200b Efecto: Funcionalidad reducida, notificaciones fallidas \n\u25cf\u200b Trigger: > 20% de usuarios reportan problemas de conexi\u00f3n \nAdem\u00e1s de las soluciones t\u00e9cnicas previamente descritas, estableceremos alianzas \nestrat\u00e9gicas con proveedores de internet para ofrecer planes especiales a nuestros \nusuarios. Desarrollaremos una versi\u00f3n b\u00e1sica con funcionalidad offline completamente \naut\u00f3noma para usuarios en zonas con conectividad limitada. \n \n2.3 Resumen Cuantitativo de Riesgos Identificados \nCategor\u00eda \nCantidad \nPorcentaje \nT\u00e9cnicos \n3 \n33% \nFinancieros \n1 \n11% \nOperativos \n2 \n22% \nMercado \n1 \n11% \nRRHH \n1 \n11% \nExternos \n1 \n11% \nTOTAL \n9 \n100% \n2.4 Triggers y Se\u00f1ales de Alerta Temprana \nEl equipo de proyecto monitorear\u00e1 las siguientes se\u00f1ales para activar respuestas: \nSe\u00f1ales T\u00e9cnicas: \n\u25cf\u200b Tasa de fallos en pruebas > 5% \n\u25cf\u200b Duraci\u00f3n de bater\u00eda < 90% especificaci\u00f3n \n\u25cf\u200b Latencia de sincronizaci\u00f3n > 3 segundos \nSe\u00f1ales Financieras: \n\u25cf\u200b Cotizaciones > 10% del presupuesto \n\u25cf\u200b Desviaci\u00f3n acumulada > 8% \nSe\u00f1ales Operativas: \n\u25cf\u200b Retrasos > 1 semana en entregables \n\u25cf\u200b Proveedores con calificaci\u00f3n < 4/5 \nSe\u00f1ales de Mercado: \n\u25cf\u200b Satisfacci\u00f3n en piloto < 70% \n\u25cf\u200b Tasa de abandono > 25% \nSe\u00f1ales de RRHH: \n\u25cf\u200b Ausencias no justificadas \n\u25cf\u200b Disminuci\u00f3n en calidad de entregables \nSe\u00f1ales Externas: \n\u25cf\u200b Anuncios de cambios regulatorios \n\u25cf\u200b Problemas reportados en zona de pruebas \n3. Registro de Riesgos (Risk Register) \nID \nCategor\u00ed\na \nCausa \nEvento \n(Riesgo) \nEfecto en el \nProyecto \nProb. \nIm\npa\ncto \nNivel \nEstrategia \nResponsable \nEstado \nR1 \nT\u00e9cnico \nFallo en la \ncomunicac\ni\u00f3n IoT \nApp \ny \npastillero \nno \nse \nsincroniz\nan \nRetrasos, \np\u00e9rdida de \nconfianza \nM \nA \nCr\u00edtic\no \nMitigar: \npruebas \ntempranas \ny \nredundanci\na \nBluetooth \n+ WiFi \nJahir \nFlores \nZaragoza \n(L\u00edder \nFirmware) y David \nAlejandro \nToledo \nDur\u00e1n (L\u00edder HW) \nAbierto \nR2 \nT\u00e9cnico \nComponen\ntes \ndefectuoso\ns \no \nbaja \nbater\u00eda \nPastillero \nse apaga \nantes \nde \nlo \nesperado \nBaja \nconfiabilida\nd \nM \nM \nModer\nado \nMitigar: \ncontrol de \ncalidad \ny \nmejores \nproveedore\ns \nDavid Toledo Dur\u00e1n \n(L\u00edder HW) \nAbierto \nR3 \nFinancie\nro \nAumento \nde precios \nelectr\u00f3nico\ns \nSobrecost\nos \nen \nprototipa\ndo \n+15% \npresupuest\no \nM \nM \nModer\nado \nTransferir: \ncontratos \nde \nprecio \nfijo \nSergio Uriel Garc\u00eda \nHern\u00e1ndez (Gerente \nde Proyecto) \nAbierto \n \n4. Matriz Probabilidad\u2013Impacto \nClasificaci\u00f3n de riesgos:\u200b\n - Cr\u00edticos (zona roja): R1, R4, R5, R6\u200b\n - Altos (zona naranja): R8\u200b\n - Moderados (zona amarilla): R2, R3, R7, R9\u200b\n - Bajos (zona verde): Ninguno \n\u200b\n\u200b\n \n \n \n \n \n \n \n \nR4 \nOperativ\no \nComplejida\nd \nen \ndesarrollo \napp \nRetraso \nen \nentregabl\nes \n+4 semanas \n(22% \ncronograma\n) \nA \nA \nCr\u00edtic\no \nMitigar: \nmodulariza\nci\u00f3n \ny \nentregas \nparciales \nOsvaldo \nJuarez \nTlamani (L\u00edder App \nM\u00f3vil) \nAbierto \nR5 \nOperativ\no \nDependenc\nia \nde \nensamblaje \nexterno \nRetrasos \nde \nproveedor \nExtensi\u00f3n \nde \ncronograma \nM \nA \nCr\u00edtic\no \nTransferir: \ncontrato \nSLA, \nproveedor \nalterno \nSergio Uriel Garc\u00eda \nHern\u00e1ndez (Gerente \nde Proyecto) \nAbierto \nR6 \nMercad\no \nPoca \naceptaci\u00f3n \nadultos \nmayores \nBaja \nadopci\u00f3n \nRiesgo \ncomercial \nM \nA \nCr\u00edtic\no \nMitigar: \npruebas \npiloto \ny \nmarketing \ndirigido \nMar\u00eda \nFernanda \nAguas \nRojas \ny \nIsrael \nIgnacio \nCalder\u00f3n \nPaisano \n(Analistas \nde \nNegocio) \nAbierto \nR7 \nRRHH \nRotaci\u00f3n \nde \npersonal \nclave \nP\u00e9rdida \nde \nconocimi\nento \nRetrasos y \nerrores \nB \nM \nModer\nado \nMitigar: \ndocumenta\nci\u00f3n, \ntransferenc\nia \nde \nconocimie\nnto \nSergio Uriel Garc\u00eda \nHern\u00e1ndez (Gerente \nde Proyecto) \nAbierto \nR8 \nExterno \nCambio \nnormativas \nm\u00e9dicas \nNuevos \nrequisitos \nlegales \nRedise\u00f1o, \nsobrecosto\ns \nB \nA \nAlto \nAceptar/Mit\nigar: \nmonitoreo \nregulatorio \ny asesor\u00eda \nlegal \nMar\u00eda \nFernanda \nAguas \nRojas \ny \nIsrael \nIgnacio \nCalder\u00f3n \nPaisano \n(Analistas \nde \nNegocio) \nAbierto \nR9 \nExterno \nFallas \nde \nconectivid\nad \nen \nusuarios \nSin \nsincroniz\naci\u00f3n \nremota \nNotificacion\nes fallidas \nM \nM \nModer\nado \nMitigar: \nmodo \noffline con \nalertas \nlocales \nJahir \nFlores \nZaragoza \n(L\u00edder \nFirmware) \nAbierto \n \n \n La matriz de probabilidad\u2013impacto se representa de forma visual en el an\u00e1lisis, donde se \nobserva la ubicaci\u00f3n de cada riesgo seg\u00fan su probabilidad y su impacto. \n5. Estrategia de Monitoreo \n\u2022 Reuniones quincenales de riesgos.\u200b\n \u2022 Actualizaci\u00f3n del Registro de Riesgos tras cada fase.\u200b\n \u2022 Revisi\u00f3n de supuestos y controles de calidad en cada hito.\u200b\n \u2022 Documentar lecciones aprendidas para futuros proyectos. \n\u00a1Por supuesto! Aqu\u00ed tienes una versi\u00f3n m\u00e1s extendida y detallada de las conclusiones, \nelaborada a partir de la informaci\u00f3n del documento. \n \nConclusiones \nEl proyecto \"Pastillero Inteligente\" concluye su fase de planificaci\u00f3n present\u00e1ndose como \nuna soluci\u00f3n integral y robusta, dise\u00f1ada para responder de manera efectiva a la \nproblem\u00e1tica de salud p\u00fablica que representa la polimedicaci\u00f3n en adultos mayores. La \ninvestigaci\u00f3n inicial y la conformaci\u00f3n de la idea han validado la necesidad cr\u00edtica de una \nherramienta que mejore la adherencia terap\u00e9utica, y los estudios de viabilidad y factibilidad \nconfirman que la propuesta es alcanzable y pertinente. Se ha determinado que el proyecto \nes viable gracias a la disponibilidad de tecnolog\u00eda de bajo costo y a la existencia de un \nmercado amplio con una necesidad social clara. Asimismo, es factible porque se basa en la \nimplementaci\u00f3n de componentes ya existentes y en un dise\u00f1o centrado en el usuario, lo que \ngarantiza su facilidad de uso y adaptaci\u00f3n a las rutinas de los pacientes y cuidadores. \nLa fortaleza principal del proyecto reside en su exhaustiva y meticulosa planificaci\u00f3n, que \nabarca todas las \u00e1reas de gesti\u00f3n fundamentales. El cronograma de 18 semanas, con hitos \nbien definidos, ofrece una hoja de ruta clara para la ejecuci\u00f3n, desde el dise\u00f1o hasta las \npruebas piloto con usuarios. La gesti\u00f3n de costos ha permitido establecer un presupuesto \nsimulado de $116,725 MXN, una inversi\u00f3n controlada que asegura la viabilidad econ\u00f3mica \ndel desarrollo del prototipo. Adem\u00e1s, la definici\u00f3n clara de roles y responsabilidades para \ncada miembro del equipo garantiza una cobertura completa de las \u00e1reas de hardware, \nsoftware, an\u00e1lisis y gesti\u00f3n, sentando las bases para un flujo de trabajo eficiente y \ncolaborativo. \nUn pilar fundamental de esta planificaci\u00f3n ha sido la gesti\u00f3n proactiva de riesgos. Se \nidentificaron y analizaron sistem\u00e1ticamente nueve riesgos principales, abarcando categor\u00edas \nt\u00e9cnicas, financieras, operativas y de mercado. La clasificaci\u00f3n de riesgos cr\u00edticos como el \nretraso en el desarrollo de la aplicaci\u00f3n m\u00f3vil (R4), la dependencia de un proveedor externo \n(R5) o la baja adopci\u00f3n por parte de los usuarios (R6), ha permitido la formulaci\u00f3n de \nestrategias de mitigaci\u00f3n espec\u00edficas antes de que estos puedan impactar el proyecto. Este \nenfoque realista y previsor es un factor clave que incrementa significativamente las \nprobabilidades de \u00e9xito. \nEn resumen, el proyecto \"Pastillero Inteligente\" trasciende la mera concepci\u00f3n de un \ndispositivo tecnol\u00f3gico para posicionarse como una iniciativa bien estructurada con un \nprofundo potencial de impacto social. Cumple con su misi\u00f3n de ofrecer una soluci\u00f3n que \nbrinde seguridad a los pacientes y apoyo a sus cuidadores , y traza un camino claro hacia \nsu visi\u00f3n de futuro: ser una herramienta innovadora que reduce hospitalizaciones y aumente \nla autonom\u00eda y calidad de vida de los adultos mayores. La culminaci\u00f3n exitosa de esta fase \nde planificaci\u00f3n demuestra que el equipo posee no solo la capacidad t\u00e9cnica, sino tambi\u00e9n \nla madurez en gesti\u00f3n de proyectos necesaria para transformar esta idea en una realidad \ntangible y beneficiosa para la sociedad. \nEvaluaci\u00f3n de madurez bajo CMMI \nNiveles del modelo CMMI \n1.\u200b Inicial - proceso improvisado, dependiente de personas. \n2.\u200b Gestionado - pr\u00e1cticas b\u00e1sicas documentadas, control de proyecto. \n3.\u200b Definido - procesos estandarizados, institucionalizados. \n4.\u200b Cuantitativamente gestionado - gesti\u00f3n basada en datos y m\u00e9tricas. \n5.\u200b Optimizado - mejora continua y an\u00e1lisis predictivo. \n \nMetodolog\u00eda de evaluaci\u00f3n \nLa evaluaci\u00f3n se realiz\u00f3 mediante un an\u00e1lisis del documento, comparando la evidencia \ndisponible contra los requisitos del modelo CMMI. Se utilizaron criterios como \ndocumentaci\u00f3n, estandarizaci\u00f3n, m\u00e9tricas, control cuantitativo y mejora continua. \n \nEvaluaci\u00f3n del proceso: Gesti\u00f3n de Riesgos \n \nRequisito CMMI \nEvidencia \nCumplimiento \nNivel 2: Documentaci\u00f3n \nMetodolog\u00eda formal PMBOK \nSi \nNivel 3: Estandarizaci\u00f3n \nT\u00e9cnicas estructurales: \nFODA, entrevistas \nSi \nNivel 4: M\u00e9tricas \nKPIs, triggers, matriz \nprob-impacto \nSi \nNivel 5: Mejora continua \nNo hay ciclos hist\u00f3ricos \nParcial \n \nNivel asignado: 4 - Cuantitativamente Gestionado \n \nEvaluaci\u00f3n del proceso: Gesti\u00f3n de Calidad \n \nRequisito CMMI \nEvidencia \nCumplimiento \nNivel 2: Documentaci\u00f3n \nKPIs, plan de pruebas \nSi \nNivel 3: Estandarizaci\u00f3n \nRevisi\u00f3n semanales, Git \nSi \nNivel 4: Control cuantitativo \nNo existen mediciones \nreales \nNo \nNivel 5: Mejora continua \nSin tendencias ni \nretroalimentaci\u00f3n iterativa \nNo \n\u200b\n \nNivel asignado: 3 - Definido \n \nRecomendaciones para subir de nivel \n \nGesti\u00f3n de riesgos \n-\u200b\nImplementar an\u00e1lisis hist\u00f3rico de tendencias. \n-\u200b\nRealizar ciclos formales de retroalimentaci\u00f3n. \n-\u200b\nIncorporar dashboards autom\u00e1ticos para KPIs. \n-\u200b\nIntegrar an\u00e1lisis predictivo. \n \nGesti\u00f3n de calidad \n-\u200b\nRegistrar datos del desempe\u00f1o. \n-\u200b\nImplementar m\u00e9tricas estad\u00edsticas. \n-\u200b\nUsar control estad\u00edstico de procesos. \n-\u200b\nDocumentar lecciones aprendidas. \n \nComparaci\u00f3n de Madurez \n \nCriterio \nRiesgos \nCalidad \nNivel CMMI  \n4 \n3 \nDocumentaci\u00f3n \nAlta \nAlta \nM\u00e9tricas \nSi \nParcial \nMejora continua \nParcial \nNo \n \nConclusi\u00f3n  \nEl proceso de Gesti\u00f3n de Riesgos demuestra una madurez superior al alcanzar el nivel 4 \ndel modelo CMMI, debido a su estructura basada en datos, triggers, monitoreo continuo y \nestrategias definidas. Por su parte, Gesti\u00f3n de Calidad se ubica en el nivel 3, ya que est\u00e1 \ndocumentado y estandarizado, pero a\u00fan carece de mediaciones cuantitativas y control \nestad\u00edstico. Ambos procesos presentan un desarrollo adecuado, destacando la robustez del \nproceso de riesgos. \n \n \n \n \n \n \nMatrices RACI del proyecto \n \nMatriz RACI - proceso 04 Definir los procesos, Organizaci\u00f3n y \nRelaciones de TI \n \n \nJustificaci\u00f3n de Asignaciones \n\u25cf\u200b Responsable (R): L\u00edder de Software/Firmware y L\u00edder de Apps M\u00f3viles. \n\u25cb\u200b Ambos son los responsables de desarrollar el c\u00f3digo y, por lo tanto, son los \nencargados directos de definir el marco de trabajo (lenguajes, frameworks, \nest\u00e1ndares de codificaci\u00f3n, herramientas de control de versiones como Git) \npara sus respectivas \u00e1reas (firmware embebido y aplicaci\u00f3n m\u00f3vil). \n\u25cf\u200b Aprobador (A): Gerente de Proyecto (Sergio Uriel). \n\u25cb\u200b El Gerente de Proyecto aprueba el marco de trabajo, asegurando que los \nest\u00e1ndares definidos se alineen con el cronograma de 18 semanas, el \npresupuesto de costes y la capacidad general del equipo. \n\u25cf\u200b Consultados (C): L\u00edder de Hardware y Analistas de Negocio/Calidad. \n\u25cb\u200b El L\u00edder de Hardware es consultado para asegurar que el marco de trabajo \nde \nsoftware \nsea \ncompatible \ncon \nla \nconectividad \ny el hardware \n(Bluetooth/WiFi, bajo consumo). \n\u25cb\u200b Los Analistas de Negocio/Calidad son consultados para asegurar que el \nmarco incluya los procesos de pruebas de calidad necesarios para cumplir \ncon los KPI de confiabilidad. \n \n \nJustificaci\u00f3n de la Actividad: Dise\u00f1ar Marco de Trabajo \npara el Proceso de TI \nEsta actividad es la base de la Planificaci\u00f3n de la Calidad y la ejecuci\u00f3n t\u00e9cnica. Se \njustifica su inclusi\u00f3n porque define la estructura t\u00e9cnica que asegurar\u00e1 el cumplimiento de \nlos requerimientos y la mitigaci\u00f3n de riesgos operativos. \n1. Soporte a la Ejecuci\u00f3n T\u00e9cnica y Calidad (\u00bfC\u00f3mo aseguramos la \nconfiabilidad?) \n\u25cf\u200b Definici\u00f3n de Est\u00e1ndares de Calidad: Esta tarea define los est\u00e1ndares de \ndesarrollo que se utilizar\u00e1n para cumplir los Requerimientos No Funcionales (ej., \nInterfaz simple e intuitiva y Conectividad segura). Un marco de trabajo claro \nasegura que el c\u00f3digo sea revisable y escalable. \n\u25cf\u200b Alineaci\u00f3n con el Prototipado: Al definir el marco, se seleccionan las herramientas \nque permitir\u00e1n una Programaci\u00f3n del firmware eficiente y un Desarrollo de la \naplicaci\u00f3n m\u00f3vil r\u00e1pido, lo cual es crucial para encajar estas tareas en el tiempo \najustado de 6 y 4 semanas respectivamente, dentro del cronograma de 18 \nsemanas. \n2. Mitigaci\u00f3n del Riesgo Operativo y T\u00e9cnico \n\u25cf\u200b Respuesta al Riesgo R4 (Retraso en desarrollo de aplicaci\u00f3n m\u00f3vil): Un marco \nde trabajo bien definido, que incluye el uso de metodolog\u00edas \u00e1giles y herramientas \nde control de versiones (Git), previene la \"complejidad t\u00e9cnica subestimada\" al \nestandarizar el proceso y permitir la modularizaci\u00f3n de entregables parciales. \n\u25cf\u200b Respuesta al Riesgo R1 (Fallo en la comunicaci\u00f3n IoT): El marco de trabajo \nobliga a los l\u00edderes t\u00e9cnicos a establecer protocolos de comunicaci\u00f3n y redundancia \n(Bluetooth + WiFi) desde la fase de dise\u00f1o, lo cual es la estrategia de mitigaci\u00f3n de \neste riesgo. \n3. Impacto en la Gesti\u00f3n de Costes \n\u25cf\u200b Justificaci\u00f3n de Coste de Software: La definici\u00f3n del marco de trabajo justifica la \ninversi\u00f3n en Plataformas de Desarrollo (3,500 MXN), ya que se seleccionan \nexpl\u00edcitamente las licencias o servicios necesarios para las herramientas de dise\u00f1o \nUI/UX y la plataforma multiplataforma (Flutter/React Native) que ser\u00e1n utilizadas por \nlos responsables (R) del dise\u00f1o. \n \n \n \n \n \n \nMatriz RACI - P07 Administrar los Recursos Humanos de TI \n \nJustificaci\u00f3n de Asignaciones \n\u25cf\u200b Identificaci\u00f3n de Habilidades y Benchmarks: \n\u25cb\u200b Responsable (R): Analistas de Negocio/Calidad (Maria Fernanda y Israel). \nSu rol de Analista de Negocio es recopilar informaci\u00f3n, definir los KPIs y \nrealizar la investigaci\u00f3n de mercado y de capital humano para establecer los \nbenchmarks. \n\u25cb\u200b Aprobador (A): El Gerente de Proyecto (Sergio Uriel) aprueba formalmente \nlas descripciones de puestos y los rangos salariales simulados, ya que es el \ndue\u00f1o final de la gesti\u00f3n del presupuesto (Costes). \n \nJustificaci\u00f3n \nde \nla \nActividad: \nIdentificaci\u00f3n \nde \nHabilidades \ny \nBenchmarks \nEsta actividad es esencialmente la Planificaci\u00f3n de los Recursos Humanos del proyecto. \nSe justifica su inclusi\u00f3n porque, aunque el proyecto no es real, la documentaci\u00f3n debe \nreflejar los pasos necesarios para garantizar la calidad y la competitividad del equipo. \n1. Soporte a la Viabilidad y Competitividad del Proyecto \n\u25cf\u200b Fundamento de Viabilidad: Para que el proyecto sea viable, debemos demostrar \nque la empresa puede atraer y retener el talento necesario. Identificar las \nhabilidades de TI (como la programaci\u00f3n embebida, el desarrollo multiplataforma y \nla arquitectura en la nube) es crucial para confirmar que el proyecto es t\u00e9cnicamente \nrealizable con personal real. \n\u25cf\u200b Definici\u00f3n de Benchmarks: La investigaci\u00f3n sobre benchmarks y salarios \nestablece el coste simulado del recurso humano, validando la secci\u00f3n de Gesti\u00f3n \nde Costes (Recursos Humanos: 54,000 MXN ) y asegurando que la estimaci\u00f3n sea \ncre\u00edble y competitiva en el sector tecnol\u00f3gico. \n2. Base para la Evaluaci\u00f3n y el Desarrollo del Personal \n\u25cf\u200b Definici\u00f3n de Roles de Calidad: Esta actividad garantiza que las descripciones \nde puesto sean claras y est\u00e9n alineadas con los objetivos de calidad del proyecto. \nEsto incluye definir los requisitos para la interfaz simple e intuitiva (para el \nDise\u00f1ador \nde \nUI/UX) \ny \nla \nconectividad \nsegura \n(para \nel \nL\u00edder \nde \nSoftware/Firmware). \n\u25cf\u200b Soporte a Planes de Carrera: La matriz RACI y esta actividad sirven de base para \nel Plan de Carrera de Personal. Al identificar las habilidades actuales y las \nnecesidades de desarrollo, el proyecto puede justificar el entrenamiento y la \npromoci\u00f3n futura, cumpliendo el objetivo de preparar a los integrantes para roles \navanzados en el mercado laboral. \n3. Mitigaci\u00f3n del Riesgo de Recursos Humanos \n\u25cf\u200b Respuesta al Riesgo R7: Esta planificaci\u00f3n de personal es una respuesta proactiva \nal Riesgo R7 - Rotaci\u00f3n de personal clave del equipo. Al definir rangos \ncompetitivos y un plan de desempe\u00f1o (benchmarks), se minimiza la causa de la \nrotaci\u00f3n (insatisfacci\u00f3n o baja participaci\u00f3n ), aumentando la probabilidad de \nretener el conocimiento esencial y evitar retrasos y errores. \n \nMatriz RACI - P10 Administrar proyectos \n \nJustificaci\u00f3n de Asignaciones \n\u25cf\u200b Responsable (R): Gerente de Proyecto (Sergio Uriel). \n\u25cb\u200b Como l\u00edder general, el Gerente de Proyecto es el responsable directo de la \ncomunicaci\u00f3n con las partes interesadas y de gestionar la alineaci\u00f3n del \nproyecto con la Misi\u00f3n y Visi\u00f3n. Su rol principal es asegurar que el equipo \nest\u00e9 coordinado y que los stakeholders externos (cuidadores, docentes, \nposibles inversionistas) se mantengan comprometidos. \n\u25cf\u200b Aprobador (A): Analistas de Negocio/Calidad (Maria Fernanda y Israel). \n\u25cb\u200b Los Analistas de Negocio son los due\u00f1os de la recopilaci\u00f3n de \nrequerimientos y tienen el conocimiento m\u00e1s profundo de las necesidades \nde los usuarios (adultos mayores y cuidadores). Por lo tanto, aprueban que \nlas estrategias de comunicaci\u00f3n y el nivel de compromiso sean suficientes \npara que el producto final tenga \u00e9xito en el mercado. \n\u25cf\u200b Consultado (C): L\u00edder de Hardware/Electr\u00f3nica. \n\u25cb\u200b Se consulta al L\u00edder de Hardware sobre la capacidad t\u00e9cnica de cumplir con \nlas expectativas del mercado (ej. Bajo consumo de energ\u00eda, durabilidad). Su \nfeedback es crucial para no prometer caracter\u00edsticas que el hardware no \npueda entregar. \n\u25cf\u200b Informado (I): L\u00edder de Software/Firmware y L\u00edder de Apps M\u00f3viles. \n\u25cb\u200b Los l\u00edderes de desarrollo son informados sobre el estado de la participaci\u00f3n \nde los interesados para que puedan priorizar tareas y entender c\u00f3mo el \nfeedback del mercado impacta el desarrollo de las funcionalidades. \nJustificaci\u00f3n de la Actividad: Asegurar la Participaci\u00f3n y Compromiso \nEsta actividad se justifica porque el \u00e9xito del Pastillero Inteligente es inherentemente social, \ndependiendo de la adopci\u00f3n por parte de un p\u00fablico sensible (adultos mayores) y del apoyo \nde los cuidadores. \n1. Soporte a la Comunicaci\u00f3n y Alcance del Proyecto \n\u25cf\u200b Alineaci\u00f3n de Expectativas: Asegurar el compromiso es la base de la Gesti\u00f3n de \nComunicaciones. Esta tarea define el flujo de informaci\u00f3n para las Presentaciones \nde Avance y el Material de Marketing Inicial, asegurando que el mensaje del \nproyecto sea claro. \n\u25cf\u200b Dise\u00f1o Centrado en el Usuario: La actividad valida la estrategia de Dise\u00f1o \ncentrado en el usuario con pruebas piloto en adultos mayores (Estrategia). El \ncompromiso de los usuarios y cuidadores es vital para obtener el feedback necesario \nen las Pruebas piloto y garantizar que la interfaz simple e intuitiva sea realmente \nefectiva. \n2. Mitigaci\u00f3n del Riesgo de Mercado y Calidad \n\u25cf\u200b Respuesta al Riesgo R6 (Baja adopci\u00f3n por parte de adultos mayores): Esta \nplanificaci\u00f3n es una respuesta directa al riesgo de fracaso comercial. Al asegurar la \nparticipaci\u00f3n desde el inicio, se mitiga la causa (la \"resistencia al cambio \ntecnol\u00f3gico\" y la \"complejidad percibida\"), aumentando la tasa de satisfacci\u00f3n \ndel usuario (KPI) y evitando que la Tasa de abandono sea > 30% (Trigger de \nRiesgo). \n\u25cf\u200b Compromiso con la Calidad: Al incluir a los interesados en el proceso, se fortalece \nel cumplimiento de los Requerimientos de Dominio (ej. Integraci\u00f3n con \nnecesidades de cuidadores y personal de salud), lo que es un componente clave \npara la calidad del producto final. \n \n \nMitigaci\u00f3n del Riesgo de Mercado y Calidad \n \n \n \n \n \nGesti\u00f3n de servicios de itil  \nConcepto \nDefinici\u00f3n \nITIL \nSe define como el conjunto de buenas pr\u00e1cticas que ayudan en la \ngesti\u00f3n de un servicio, en particular un servicio de TI, su objetivo es \nalinear los servicios de TI con las necesidades del negocio mejorando \nas\u00ed la calidad y satisfacci\u00f3n del usuario. \nIncidente \nCualquier interrupci\u00f3n no planificada o reducci\u00f3n en la calidad de un \nservicio de TI. \n\u00bfCu\u00e1ndo un \nincidente se \nconvierte en un \nproblema? \n\u00b7        Se repite frecuentemente. \n\u00b7        Afecta a muchos usuarios. \n\u00b7        Requiere investigaci\u00f3n profunda para evitar que vuelva a ocurrir. \n\u00b7        Genera un impacto significativo en el negocio. \nSu causa ra\u00edz es desconocida. \nValor \nEs la importancia, utilidad y beneficio que un servicio proporciona al \ncliente, generalmente se mide en t\u00e9rminos de objetivos logrados. \nUn servicio solo tiene valor si el cliente percibe que le ayuda a lograr \nsus objetivos. \nChange \nManagement \nProceso responsable de controlar el ciclo de vida de todos los \ncambios en los servicios de TI. Su objetivo es minimizar el riesgo y el \nimpacto negativo que un cambio pueda causar en los servicios \nactivos. \nChange \nEs cualquier modificaci\u00f3n en servicios de TI que puede afectar el \nfuncionamiento del sistema. \nRFC \nEs la solicitud formal para implementar un cambio, contiene detalles \nsobre el cambio como su impacto, riesgos y plan de implementaci\u00f3n. \nService \nMedio para entregar valor al cliente facilitando los resultados que \nquieren lograr sin que el cliente deba gestionar costos o riesgos \nespec\u00edficos. \nChange \nManagement \nProcess \nSe refiere al flujo de trabajo espec\u00edfico que sigue un cambio (RFC) \ndesde su creaci\u00f3n hasta su cierre. T\u00edpicamente incluye pasos como: \nRegistro, Evaluaci\u00f3n y Autorizaci\u00f3n (evaluando riesgo e impacto), \nPlanificaci\u00f3n, Implementaci\u00f3n y Revisi\u00f3n. \nIncident \nManagement \nEs la pr\u00e1ctica responsable de gestionar todos los incidentes. Su \nobjetivo principal es restaurar la operaci\u00f3n normal del servicio lo m\u00e1s \nr\u00e1pido posible y minimizar el impacto adverso en las operaciones del \nnegocio. \nProblema \nManagement \nEs la pr\u00e1ctica responsable de gestionar todos los problemas. Su \nobjetivo es identificar la causa ra\u00edz de los incidentes, encontrar \nsoluciones (temporales o definitivas) y prevenir que los incidentes \nocurran o se repitan. \nOperation \nManagement \nSe refiere a la Gesti\u00f3n de Operaciones de TI. Es la funci\u00f3n que se \nencarga de supervisar y controlar la infraestructura y los servicios de \nTI en el d\u00eda a d\u00eda. Se asegura de que todo funcione de manera \nestable y predecible. \nConfiguration Item \nUn Elemento de Configuraci\u00f3n (CI) es cualquier activo o componente \n(hardware, software, documentaci\u00f3n, personal) que necesita ser \ngestionado para poder entregar un servicio de TI. Los CIs y sus \nrelaciones se registran en una Base de Datos de Gesti\u00f3n de la \nConfiguraci\u00f3n (CMDB). \nProcesos y actividades de atenci\u00f3n de Change Management  \nFASE \nNOMBRE DEL \nPROCESO \nACTIVIDADES \n1 \nInicializaci\u00f3n \n1. Preguntas clave de ingenier\u00eda de software (RFC - Request For \nChange): \na) \u00bfQu\u00e9? (El cambio): A\u00f1adir una pantalla LCD/OLED de bajo \nconsumo al pastillero f\u00edsico para mostrar la hora actual, el nombre \ndel medicamento pr\u00f3ximo y la dosis, reduciendo la dependencia de \nla app m\u00f3vil para la informaci\u00f3n inmediata. \nb) \u00bfCu\u00e1ndo? (Implementaci\u00f3n) \nIdealmente, debe integrarse durante la Fase de Desarrollo y Pruebas \n(Semanas 9-16) para ser incluido en el prototipo funcional del Hito 3. \nc) \u00bfPor qu\u00e9? (Justificaci\u00f3n) \nMitigar directamente el Riesgo R6 (Baja adopci\u00f3n) en adultos \nmayores, ya que mejora la interfaz simple e intuitiva al mostrar la \ninformaci\u00f3n cr\u00edtica directamente en el dispositivo, aline\u00e1ndose con el \nDise\u00f1o centrado en el usuario. \nd) \u00bfQui\u00e9n? (Solicitante) \nAnalistas de Negocio y Calidad (Mar\u00eda Fernanda e Israel), \nbas\u00e1ndose en la Simulaci\u00f3n de la Satisfacci\u00f3n en Piloto < 70% (una \nse\u00f1al de monitoreo). \ne) \u00bfPara qui\u00e9n? (Beneficiario)Adultos mayores (usuario final) y \nCuidadores (quienes lo gestionan). \n2. Delegar RFC: Se asigna al Gerente de Proyecto (Sergio Garc\u00eda) \npara su an\u00e1lisis formal. \n  \n2 \nDise\u00f1o del \nservicio \nEvaluaci\u00f3n de riesgo y urgencia del RFC:El cambio se clasifica como \nde Impacto Alto (requiere modificar hardware y firmware) y Urgencia \nMedia-Alta (es clave para la adopci\u00f3n/Riesgo R6). \nCreaci\u00f3n de ticket para RFC: \nSe registra formalmente en el sistema de gesti\u00f3n del proyecto, \nvincul\u00e1ndolo al Riesgo R6 y al Requerimiento No Funcional de Bajo \nConsumo de Energ\u00eda (para asegurar que la pantalla sea eficiente). \n  \nChequeo operativo del cambio con Matriz de Riesgos: \nSe activa la revisi\u00f3n del L\u00edder de Hardware (David Toledo) para \nevaluar el impacto: Aumenta el Costo Detallado del Hardware (se \nestima un 5% extra en componentes), requiere m\u00e1s Programaci\u00f3n \ndel Firmware (manejo de la pantalla) e impacta la Duraci\u00f3n de la \nBater\u00eda (Riesgo R2, que ahora podr\u00eda tener mayor Probabilidad). \n  \nNuevo Objetivo de Cambio: Aumentar la tasa de Satisfacci\u00f3n del \nUsuario al 90% en la interacci\u00f3n inicial con el hardware. \nKPI del Cambio: Reducci\u00f3n del 50% en las consultas sobre \"qu\u00e9 \ntomar\" durante las Pruebas Piloto con Usuarios (actualmente 1 \nsemana). \n  \n3 \nPlanificaci\u00f3n \nCaracterizaci\u00f3n del cambio (7 R\u2019s de Change Management): Raz\u00f3n: \nMitigar la baja adopci\u00f3n (R6). Riesgo: Aumento de costo (Riesgo \nFinanciero) y impacto en el firmware (R1). Recursos: Requiere \ntiempo \nadicional \ndel L\u00edder de Hardware y del L\u00edder de \nFirmware.Autorizaci\u00f3n del cambio: \nEl Gerente de Proyecto (Aprobador de Costes) autoriza el gasto \nadicional, entendiendo que es una mitigaci\u00f3n cr\u00edtica. \nMatrices RACI: \nSe actualiza la RACI para la actividad \"Dise\u00f1o del prototipo de \nhardware\". El L\u00edder de Hardware (David Toledo) es el R \n(Responsable), el L\u00edder de Firmware (Jahir Flores) es C \n(Consultado) y el Gerente de Proyecto (Sergio Garc\u00eda) es el A \n(Aprobador). \nGesti\u00f3n de comunicaciones: \nSe emite un Reporte de Avance Semanal extraordinario para \ninformar a todo el equipo sobre la modificaci\u00f3n del alcance (scope \ncreep) y su justificaci\u00f3n estrat\u00e9gica. \nSeguimiento y control: \nSe prioriza la revisi\u00f3n del consumo de energ\u00eda del ESP32 en los \nmodos deep-sleep con la nueva pantalla para no incumplir el \nRequerimiento No Funcional de Bajo consumo de energ\u00eda. \nCalendarizaci\u00f3n del cambio (Gr\u00e1fica de Gantt): \nSe extiende la actividad \"Dise\u00f1o del prototipo de hardware\" (3 \nsemanas) a 4 semanas y se a\u00f1ade una semana al \"Programaci\u00f3n \ndel firmware del pastillero\" (6 semanas) para integrar el driver de la \npantalla. El Hito 3 se desplaza una semana. \n  \n4 \nValidaci\u00f3n del \ncambio \nRevisi\u00f3n de KPI\u2019s: \nDurante las Pruebas piloto con usuarios, se realizan encuestas \nespec\u00edficas para medir la Satisfacci\u00f3n del usuario con la nueva \npantalla. Se verifica que las consultas sobre \"qu\u00e9 tomar\" se hayan \nreducido seg\u00fan el objetivo establecido. \n  \n5 \nImplementaci\u00f3n \ndel cambio \nProceso PDCA (Planificar, Hacer, Verificar, Actuar): Hacer: El L\u00edder \nde Hardware suelda la pantalla; el L\u00edder de Firmware sube el c\u00f3digo \nnuevo al ESP32. \nVerificar: El Analista de Calidad ejecuta Pruebas de integraci\u00f3n del \nsistema para confirmar que la pantalla no genere fallos en la \nsincronizaci\u00f3n (R1) y que la bater\u00eda a\u00fan cumpla con las \nespecificaciones (R2). \n  \n6 \nRevisi\u00f3n y \nliberaci\u00f3n de \ncambios. \nHacer pruebas y documentaci\u00f3n: \nSe documenta formalmente la decisi\u00f3n en el Registro de Riesgos \n(Risk Register), cerrando la mitigaci\u00f3n del Riesgo R6. Se actualiza el \nCoste Detallado del Hardware y se incorpora la pantalla en las \nConclusiones finales y presentaci\u00f3n del proyecto como una mejora \nclave de usabilidad. \n  \n \nDiagrama de flujo\n \nPreguntas Claras \n1. Integraci\u00f3n de PMBOK y Alcance \n1.\u200b Validaci\u00f3n del Alcance: El Pastillero Inteligente debe ser capaz de enviar \nnotificaciones a los cuidadores (Requerimiento Funcional). \u00bfC\u00f3mo se llama el \ndocumento clave del PMBOK que el Analista de Negocio debe usar para que \nel L\u00edder de Desarrollo de Apps M\u00f3viles demuestre formalmente que esta \nfuncionalidad de notificaci\u00f3n fue construida correctamente y que el cliente \n(simulado) la acept\u00f3? \n2.\u200b Gesti\u00f3n del Cronograma: La actividad de Programaci\u00f3n del Firmware se \nextendi\u00f3 de 6 a 7 semanas debido al cambio de la pantalla LCD. \u00bfC\u00f3mo se \nllama el documento central del PMBOK que el Gerente de Proyecto debe \nactualizar formalmente para reflejar este nuevo plazo? \n2. Calidad y Madurez (CMMI) \n3.\u200b Objetivo de Calidad: Nuestro Objetivo de Calidad es garantizar que el \npastillero funcione con un 90% de confiabilidad en las alertas. \u00bfQu\u00e9 \nherramienta de Planificaci\u00f3n de la Calidad (PMBOK) usar\u00eda el equipo para \ndeterminar si se necesita la certificaci\u00f3n b\u00e1sica en un dispositivo m\u00e9dico? \n4.\u200b Madurez CMMI: Si nuestro equipo quiere alcanzar un nivel de madurez \nCMMI Nivel 2 (Gestionado), \u00bfqu\u00e9 proceso de gesti\u00f3n del proyecto debemos \ndocumentar, entrenar y seguir rigurosamente para garantizar que no \nvolvamos a cometer el mismo error de estimaci\u00f3n de tiempo (R4: Retraso \nen desarrollo de aplicaci\u00f3n m\u00f3vil)? \n3. Gesti\u00f3n de Servicios (ITIL) \n5.\u200b Valor del Servicio: \u00bfCu\u00e1l es el Servicio que realmente entregamos al \ncliente (Cuidador) y c\u00f3mo el cambio de la pantalla LCD impacta el Valor \npercibido por el Usuario (Adulto Mayor)? \n6.\u200b Tipos de Cambio: El proceso de a\u00f1adir la pantalla LCD fue una solicitud \nformal. Describa brevemente la diferencia entre un Cambio Normal (RFC) y \nun Cambio de Emergencia (ITIL) en el contexto de nuestro proyecto (ej. \n\u00bfQu\u00e9 tipo de cambio ser\u00eda un fallo de seguridad cr\u00edtico en el servidor de \nnotificaciones?) \n \nCONCLUSIONES \nLa realizaci\u00f3n de este proyecto, consistente en el desarrollo de un sistema de \npastillero inteligente integrado con una aplicaci\u00f3n m\u00f3vil para combatir la \npolimedicaci\u00f3n en adultos mayores, ha trascendido el mero ejercicio t\u00e9cnico de \nprogramaci\u00f3n y electr\u00f3nica. Nos ha permitido comprender que la viabilidad de una \nsoluci\u00f3n tecnol\u00f3gica no depende \u00fanicamente de que \"el c\u00f3digo funcione\" o el \ncircuito cierre, sino de una gesti\u00f3n estructurada que asegure calidad, seguridad y \nvalor para el usuario final. \nA continuaci\u00f3n, presentamos nuestras reflexiones sobre la integraci\u00f3n de las \nmetodolog\u00edas de gesti\u00f3n y gobierno de TI en nuestro proceso de desarrollo: \nReflexi\u00f3n sobre PMBOK (Project Management Body of Knowledge) \nDesde la perspectiva acad\u00e9mica, la implementaci\u00f3n de los lineamientos del PMBOK \nfue fundamental para transformar una \"idea abstracta\" en un proyecto ejecutable. Al \ninicio, subestimamos la importancia de la Gesti\u00f3n del Alcance y la Gesti\u00f3n de \nRiesgos. Sin embargo, aplicar este est\u00e1ndar nos oblig\u00f3 a definir claramente qu\u00e9 no \nhar\u00eda el sistema (limit\u00e1ndolo a recordatorios y no a dispensaci\u00f3n m\u00e9dica cr\u00edtica), lo \ncual salv\u00f3 al equipo de comprometerse con funcionalidades inalcanzables en el \ncronograma de 18 semanas. PMBOK nos ense\u00f1\u00f3 a respetar la \"Triple Restricci\u00f3n\" \n(Alcance, Tiempo y Costo), entendiendo que cualquier cambio en los requerimientos \nimpacta directamente en la calidad del entregable final. \nReflexi\u00f3n sobre ITIL (Information Technology Infrastructure Library) \nLa incorporaci\u00f3n de ITIL cambi\u00f3 nuestro enfoque de \"crear un producto\" a \"proveer \nun servicio\". Acad\u00e9micamente, esto fue un punto de inflexi\u00f3n. Comprendimos que el \npastillero y la app no son el fin, sino el medio para entregar valor: la salud del \npaciente. Bajo la \u00f3ptica de ITIL, nos enfocamos en el dise\u00f1o del servicio (Service \nDesign) y la operaci\u00f3n (Service Operation), priorizando la Alta Disponibilidad y la \ngesti\u00f3n de incidencias. Entendimos que, si el servidor en la nube falla o la bater\u00eda se \nagota, el servicio se interrumpe y el valor para el usuario desaparece. ITIL nos dot\u00f3 \ndel lenguaje necesario para planificar el soporte y la continuidad del servicio m\u00e1s \nall\u00e1 de la entrega del prototipo. \nReflexi\u00f3n \nsobre \nCOBIT (Control Objectives for Information and Related \nTechnologies) \nAl tratar con datos sensibles de salud y dispositivos para adultos mayores, la \ngobernanza se volvi\u00f3 cr\u00edtica. COBIT nos proporcion\u00f3 el marco para alinear las \ntecnolog\u00edas de la informaci\u00f3n con los objetivos del negocio (en este caso, la \nadherencia terap\u00e9utica). Nuestra reflexi\u00f3n acad\u00e9mica es que COBIT act\u00faa como el \n\"\u00e1rbitro\" que asegura que la tecnolog\u00eda cumpla con las normativas y controles \nnecesarios. Nos ayud\u00f3 a identificar que la seguridad de los datos m\u00e9dicos y la \nauditor\u00eda de los registros de consumo no son caracter\u00edsticas opcionales, sino \nrequisitos de control obligatorios para mitigar riesgos legales y operativos en un \nentorno de salud. \nReflexi\u00f3n sobre CMMI (Capability Maturity Model Integration) \nFinalmente, CMMI nos ofreci\u00f3 una visi\u00f3n clara sobre la madurez de nuestros \nprocesos de desarrollo. Como estudiantes, a menudo operamos en un nivel de \nmadurez \"Inicial\" (ca\u00f3tico y dependiente del esfuerzo individual o heroico). La \nreflexi\u00f3n al estudiar CMMI es que, para profesionalizarnos, debemos aspirar al nivel \n\"Gestionado\" y posteriormente \"Definido\". Intentamos aplicar esto documentando \nnuestros procesos, estandarizando la forma en que escribimos c\u00f3digo (backend y \nfirmware) y estableciendo pruebas de calidad recurrentes. CMMI nos ense\u00f1\u00f3 que la \ncalidad del software es una consecuencia directa de la calidad de los procesos \nutilizados para crearlo. \nConclusi\u00f3n Final \nEn resumen, la integraci\u00f3n acad\u00e9mica de PMBOK, ITIL, COBIT y CMMI ha sido \nindispensable para dotar al proyecto de un car\u00e1cter profesional. Hemos aprendido \nque: \n1.\u200b PMBOK administra el proyecto. \n2.\u200b ITIL administra el servicio. \n3.\u200b COBIT gobierna y controla. \n4.\u200b CMMI mejora la calidad del proceso. \nComo futuros ingenieros en TICs, estas metodolog\u00edas ya no son conceptos te\u00f3ricos \nabstractos, sino herramientas vivas que nos permitieron estructurar una soluci\u00f3n \ncompleja (IoT, M\u00f3vil, Cloud) de manera eficiente, asegurando que el Pastillero \nInteligente sea no solo viable t\u00e9cnicamente, sino tambi\u00e9n sostenible, seguro y \nvalioso para la sociedad. \n \n \n \n \n \n \n \n \nReferencias  \n \n[1]Instituto Nacional de las Personas Adultas Mayores. (2024). Manual para la \nprevenci\u00f3n y atenci\u00f3n de ca\u00eddas en personas adultas mayores [PDF]. Direcci\u00f3n de \nGerontolog\u00eda, \nGobierno \nde \nM\u00e9xico. \nhttps://www.gob.mx/cms/uploads/attachment/file/929765/08_MANUAL_PARA_LA_PREVEN\nCIO_N_Y_ATENCIO_N_DE_CAI_DAS_EN_PAMS_APA.pdf \n[2]Instituto Nacional de Salud P\u00fablica. (s. f.). Ca\u00eddas en personas adultas mayores. \nInstituto \nNacional \nde \nSalud \nP\u00fablica. \nhttps://www.insp.mx/avisos/caidas-en-personas-adultas-mayores \n[3]National Institute on Aging. (s. f.). The dangers of polypharmacy and the case for \ndeprescribing \nin \nolder \nadults. \nNational \nInstitutes \nof \nHealth. \nhttps://www.nia.nih.gov/news/dangers-polypharmacy-and-case-deprescribing-older-adults \n[4]National Council on Aging. (2025). Top 10 chronic conditions affecting older adults. \nNational \nCouncil \non \nAging. \nhttps://www.ncoa.org/article/the-top-10-most-common-chronic-conditions-in-older-adults/ \n[5]Cardozo, C., Mart\u00edn, A., Salda\u00f1o, V. y Gaet\u00e1n, G. (2020). Una propuesta para mejorar \nla experiencia de los adultos mayores con las redes sociales. Tecnolog\u00eda, Ciencia y \nEducaci\u00f3n, 16, 113\u2013142 \n \n \n \n"
      }
    },
    {
      "nombre": "FB_IMG_1763078305919.jpg",
      "contenido": {
        "tipo": "texto",
        "texto": "CIRCULAR No. 030/2025\n\nC.C. Funcionarias y Funcionarios del Consejo Universitario,\n\nVicerrectores, Directoras y Directores de Unidades Acad\u00e9micas y\nDependencias Administrativas, Jefas y Jefes de Departamento,\n\nComunidad Universitaria de la Benem\u00e9rita Universidad Aut\u00f3noma de Puebla\nPresente\n\nCon fundamento en lo dispuesto por el art\u00edculo 59, fracci\u00f3n VII del Estatuto Org\u00e1nico de la Benem\u00e9rita\nUniversidad Aut\u00f3noma de Puebla y por acuerdo de la Dra. Mar\u00eda Lilia Cedillo Ram\u00edrez, Rectora de esta\nM\u00e1xima Casa de Estudios, en uso de la facultad que le confiere el art\u00edculo 56 del ordenamiento antes\ncitado, por este conducto, me permito hacer de su conocimiento lo siguiente:\n\n\u201cConforme a las solicitudes realizadas por parte de la Lic. Haydee L\u00f3pez Mosqueda y el Mtro. Carlos\nArmando R\u00edos Acevedo, en su calidad de Secretaria y Secretario General del Sindicato\nIndependiente de Trabajadores No Acad\u00e9micos (SITBUAP) y de la Asociaci\u00f3n Sindical de Personal\nAcad\u00e9mico (ASPABUAP) ambos de esta Instituci\u00f3n; se autoriza como d\u00eda no laborable el viernes 14\nde noviembre y el d\u00eda 17 de noviembre del a\u00f1o en curso, se considera como d\u00eda de descanso\nobligatorio.\n\nCon excepci\u00f3n del personal que por la naturaleza del trabajo que desempe\u00f1a no es posible su\ninterrupci\u00f3n, como lo son: el personal del Hospital Universitario de Puebla (HUP), de Radio BUAP,\nde la Direcci\u00f3n de Apoyo y Seguridad Universitaria (DASU) y de la Direcci\u00f3n de Infraestructura\nEducativa (DIE) por los trabajos que se est\u00e1n realizando en CU y CU2; en estos casos, los d\u00edas\notorgados se programar\u00e1n en t\u00e9rminos de lo previsto por la cl\u00e1usula 43 del contrato celebrado con\nel SITBUAP y de la cl\u00e1usula 52 del contrato celebrado con la ASPABUAP.\u201d\n\nAgradezco su atenci\u00f3n y reitero la seguridad de mi m\u00e1s distinguida consideraci\u00f3n.\n\nAtentamente\n\nE\n\nSecretaria Torre de Gesti\u00f3n Acad\u00e9mica y\nGeneral Servicios Administrativos,\npiso 13, (222) 229 55 00 Ext. 5023"
      }
    }
  ]
}